{
  "meta": {
    "generatedAt": "2026-07-23T22:29:35.422Z",
    "source": "build-live-from-gtfsrt.mjs",
    "feedFormat": "protobuf",
    "sourcePaths": [
      "./raw/live/vehicle-positions.pb",
      "./raw/live/tram-vehicle-positions.pb"
    ],
    "stats": {
      "rows": 1530,
      "mappedRows": 101,
      "unmappedRoutes": 1429,
      "vehicleCount": 101
    }
  },
  "vehicles": [
    {
      "id": "73DD7B678B530932DF783319BBF95E95_101",
      "label": "101",
      "routeId": "777",
      "mode": "bus",
      "tripId": "37586999-SBL 26_27-42893",
      "headsign": "Gold Coast Airport",
      "stopId": null,
      "lat": -28.05958366394043,
      "lon": 153.4379119873047,
      "bearing": null,
      "speed": null,
      "status": "stopped_at",
      "currentStopSequence": 4,
      "timestamp": 1784845752,
      "updatedAt": "2026-07-23T22:29:12.000Z"
    },
    {
      "id": "73DD7B678B530932DF783319BBF95E95_104",
      "label": "104",
      "routeId": "777",
      "mode": "bus",
      "tripId": "37587038-SBL 26_27-42893",
      "headsign": "Broadbeach South station",
      "stopId": null,
      "lat": -28.119720458984375,
      "lon": 153.47177124023438,
      "bearing": null,
      "speed": null,
      "status": "in_transit_to",
      "currentStopSequence": 3,
      "timestamp": 1784845758,
      "updatedAt": "2026-07-23T22:29:18.000Z"
    },
    {
      "id": "A7393ED51E387246BB3D6249943091E8_1041",
      "label": "1041",
      "routeId": "444",
      "mode": "bus",
      "tripId": "37813968-BT 26_27-43278",
      "headsign": "Queensland Theatre",
      "stopId": null,
      "lat": -27.51622200012207,
      "lon": 152.92550659179688,
      "bearing": null,
      "speed": null,
      "status": "in_transit_to",
      "currentStopSequence": 15,
      "timestamp": 1784845751,
      "updatedAt": "2026-07-23T22:29:11.000Z"
    },
    {
      "id": "A7393ED51E387246BB3D6249943091E8_1047",
      "label": "1047",
      "routeId": "444",
      "mode": "bus",
      "tripId": "37813859-BT 26_27-43278",
      "headsign": "Queensland Theatre",
      "stopId": null,
      "lat": -27.514694213867188,
      "lon": 152.9298553466797,
      "bearing": null,
      "speed": null,
      "status": "stopped_at",
      "currentStopSequence": 15,
      "timestamp": 1784845733,
      "updatedAt": "2026-07-23T22:28:53.000Z"
    },
    {
      "id": "73DD7B678B530932DF783319BBF95E95_105",
      "label": "105",
      "routeId": "777",
      "mode": "bus",
      "tripId": "37587001-SBL 26_27-42893",
      "headsign": "Broadbeach South station",
      "stopId": "BURLEIGH",
      "lat": -28.09347152709961,
      "lon": 153.4534149169922,
      "bearing": null,
      "speed": null,
      "status": "in_transit_to",
      "currentStopSequence": 5,
      "timestamp": 1784845756,
      "updatedAt": "2026-07-23T22:29:16.000Z"
    },
    {
      "id": "73DD7B678B530932DF783319BBF95E95_106",
      "label": "106",
      "routeId": "777",
      "mode": "bus",
      "tripId": "37587012-SBL 26_27-42893",
      "headsign": "Gold Coast Airport",
      "stopId": "BBS",
      "lat": -28.03472137451172,
      "lon": 153.4310302734375,
      "bearing": null,
      "speed": null,
      "status": "in_transit_to",
      "currentStopSequence": 1,
      "timestamp": 1784845755,
      "updatedAt": "2026-07-23T22:29:15.000Z"
    },
    {
      "id": "06EAC06E55F06AEC6418AEEBA19D5764_107",
      "label": "107",
      "routeId": "560",
      "mode": "bus",
      "tripId": "37981873-LCBS 26_27-43389",
      "headsign": "Browns Plains",
      "stopId": "LGHM",
      "lat": -27.585609436035156,
      "lon": 153.11219787597656,
      "bearing": null,
      "speed": null,
      "status": "in_transit_to",
      "currentStopSequence": 1,
      "timestamp": 1784845741,
      "updatedAt": "2026-07-23T22:29:01.000Z"
    },
    {
      "id": "73DD7B678B530932DF783319BBF95E95_109",
      "label": "109",
      "routeId": "777",
      "mode": "bus",
      "tripId": "37587003-SBL 26_27-42893",
      "headsign": "Gold Coast Airport",
      "stopId": null,
      "lat": -28.115694046020508,
      "lon": 153.46958923339844,
      "bearing": null,
      "speed": null,
      "status": "in_transit_to",
      "currentStopSequence": 12,
      "timestamp": 1784845755,
      "updatedAt": "2026-07-23T22:29:15.000Z"
    },
    {
      "id": "06EAC06E55F06AEC6418AEEBA19D5764_117",
      "label": "117",
      "routeId": "555",
      "mode": "bus",
      "tripId": "37981024-LCBS 26_27-43389",
      "headsign": "Brisbane City",
      "stopId": null,
      "lat": -27.46558380126953,
      "lon": 153.0301055908203,
      "bearing": null,
      "speed": null,
      "status": "in_transit_to",
      "currentStopSequence": 15,
      "timestamp": 1784845740,
      "updatedAt": "2026-07-23T22:29:00.000Z"
    },
    {
      "id": "06EAC06E55F06AEC6418AEEBA19D5764_118",
      "label": "118",
      "routeId": "555",
      "mode": "bus",
      "tripId": "37982242-LCBS 26_27-43389",
      "headsign": "Brisbane City",
      "stopId": "LGHM",
      "lat": -27.660776138305664,
      "lon": 153.1737823486328,
      "bearing": null,
      "speed": null,
      "status": "stopped_at",
      "currentStopSequence": 1,
      "timestamp": 1784845754,
      "updatedAt": "2026-07-23T22:29:14.000Z"
    },
    {
      "id": "06EAC06E55F06AEC6418AEEBA19D5764_121",
      "label": "121",
      "routeId": "560",
      "mode": "bus",
      "tripId": "37981286-LCBS 26_27-43389",
      "headsign": "Browns Plains",
      "stopId": null,
      "lat": -27.68808364868164,
      "lon": 153.1024932861328,
      "bearing": null,
      "speed": null,
      "status": "in_transit_to",
      "currentStopSequence": 32,
      "timestamp": 1784845764,
      "updatedAt": "2026-07-23T22:29:24.000Z"
    },
    {
      "id": "06EAC06E55F06AEC6418AEEBA19D5764_125",
      "label": "125",
      "routeId": "560",
      "mode": "bus",
      "tripId": "37982117-LCBS 26_27-43389",
      "headsign": "Loganholme station",
      "stopId": null,
      "lat": -27.686277389526367,
      "lon": 153.03500366210938,
      "bearing": null,
      "speed": null,
      "status": "stopped_at",
      "currentStopSequence": 10,
      "timestamp": 1784845756,
      "updatedAt": "2026-07-23T22:29:16.000Z"
    },
    {
      "id": "06EAC06E55F06AEC6418AEEBA19D5764_138",
      "label": "138",
      "routeId": "560",
      "mode": "bus",
      "tripId": "37981366-LCBS 26_27-43389",
      "headsign": "Browns Plains",
      "stopId": null,
      "lat": -27.664304733276367,
      "lon": 153.14508056640625,
      "bearing": null,
      "speed": null,
      "status": "in_transit_to",
      "currentStopSequence": 13,
      "timestamp": 1784845755,
      "updatedAt": "2026-07-23T22:29:15.000Z"
    },
    {
      "id": "06EAC06E55F06AEC6418AEEBA19D5764_144",
      "label": "144",
      "routeId": "555",
      "mode": "bus",
      "tripId": "37982263-LCBS 26_27-43389",
      "headsign": "Brisbane City",
      "stopId": "LGHM",
      "lat": -27.676610946655273,
      "lon": 153.2306671142578,
      "bearing": null,
      "speed": null,
      "status": "in_transit_to",
      "currentStopSequence": 1,
      "timestamp": 1784845748,
      "updatedAt": "2026-07-23T22:29:08.000Z"
    },
    {
      "id": "06EAC06E55F06AEC6418AEEBA19D5764_16",
      "label": "16",
      "routeId": "560",
      "mode": "bus",
      "tripId": "37981040-LCBS 26_27-43389",
      "headsign": "Loganholme station",
      "stopId": null,
      "lat": -27.67474937438965,
      "lon": 153.13116455078125,
      "bearing": null,
      "speed": null,
      "status": "stopped_at",
      "currentStopSequence": 38,
      "timestamp": 1784845762,
      "updatedAt": "2026-07-23T22:29:22.000Z"
    },
    {
      "id": "A7393ED51E387246BB3D6249943091E8_1641",
      "label": "1641",
      "routeId": "169",
      "mode": "bus",
      "tripId": "37820745-BT 26_27-43278",
      "headsign": "Eight Mile Plains station",
      "stopId": "UQLA",
      "lat": -27.485776901245117,
      "lon": 153.03321838378906,
      "bearing": null,
      "speed": null,
      "status": "in_transit_to",
      "currentStopSequence": 1,
      "timestamp": 1784845740,
      "updatedAt": "2026-07-23T22:29:00.000Z"
    },
    {
      "id": "A7393ED51E387246BB3D6249943091E8_1646",
      "label": "1646",
      "routeId": "169",
      "mode": "bus",
      "tripId": "37820676-BT 26_27-43278",
      "headsign": "UQ Lakes station",
      "stopId": null,
      "lat": -27.557722091674805,
      "lon": 153.0735321044922,
      "bearing": null,
      "speed": null,
      "status": "in_transit_to",
      "currentStopSequence": 3,
      "timestamp": 1784845752,
      "updatedAt": "2026-07-23T22:29:12.000Z"
    },
    {
      "id": "A7393ED51E387246BB3D6249943091E8_1838",
      "label": "1838",
      "routeId": "222",
      "mode": "bus",
      "tripId": "37814291-BT 26_27-43278",
      "headsign": "Roma Street station",
      "stopId": "CARI",
      "lat": -27.489944458007812,
      "lon": 153.1022491455078,
      "bearing": null,
      "speed": null,
      "status": "in_transit_to",
      "currentStopSequence": 1,
      "timestamp": 1784845740,
      "updatedAt": "2026-07-23T22:29:00.000Z"
    },
    {
      "id": "A7393ED51E387246BB3D6249943091E8_1928",
      "label": "1928",
      "routeId": "333",
      "mode": "bus",
      "tripId": "37822281-BT 26_27-43278",
      "headsign": "Woolloongabba station",
      "stopId": "RBWH",
      "lat": -27.44330406188965,
      "lon": 153.0295867919922,
      "bearing": null,
      "speed": null,
      "status": "in_transit_to",
      "currentStopSequence": 11,
      "timestamp": 1784845750,
      "updatedAt": "2026-07-23T22:29:10.000Z"
    },
    {
      "id": "A7393ED51E387246BB3D6249943091E8_2084",
      "label": "2084",
      "routeId": "444",
      "mode": "bus",
      "tripId": "37813368-BT 26_27-43278",
      "headsign": "Queensland Theatre",
      "stopId": "KING",
      "lat": -27.468069076538086,
      "lon": 153.02357482910156,
      "bearing": null,
      "speed": null,
      "status": "stopped_at",
      "currentStopSequence": 30,
      "timestamp": 1784845751,
      "updatedAt": "2026-07-23T22:29:11.000Z"
    },
    {
      "id": "A7393ED51E387246BB3D6249943091E8_2095",
      "label": "2095",
      "routeId": "444",
      "mode": "bus",
      "tripId": "37813617-BT 26_27-43278",
      "headsign": "Queensland Theatre",
      "stopId": null,
      "lat": -27.479387283325195,
      "lon": 152.9985809326172,
      "bearing": null,
      "speed": null,
      "status": "in_transit_to",
      "currentStopSequence": 27,
      "timestamp": 1784845736,
      "updatedAt": "2026-07-23T22:28:56.000Z"
    },
    {
      "id": "A7393ED51E387246BB3D6249943091E8_2105",
      "label": "2105",
      "routeId": "330",
      "mode": "bus",
      "tripId": "37822121-BT 26_27-43278",
      "headsign": "Queen Street station",
      "stopId": null,
      "lat": -27.456693649291992,
      "lon": 153.0183868408203,
      "bearing": null,
      "speed": null,
      "status": "in_transit_to",
      "currentStopSequence": 27,
      "timestamp": 1784845738,
      "updatedAt": "2026-07-23T22:28:58.000Z"
    },
    {
      "id": "A7393ED51E387246BB3D6249943091E8_2156",
      "label": "2156",
      "routeId": "333",
      "mode": "bus",
      "tripId": "37822286-BT 26_27-43278",
      "headsign": "Woolloongabba station",
      "stopId": "CHMS",
      "lat": -27.394805908203125,
      "lon": 153.03839111328125,
      "bearing": null,
      "speed": null,
      "status": "in_transit_to",
      "currentStopSequence": 1,
      "timestamp": 1784845747,
      "updatedAt": "2026-07-23T22:29:07.000Z"
    },
    {
      "id": "A7393ED51E387246BB3D6249943091E8_2157",
      "label": "2157",
      "routeId": "333",
      "mode": "bus",
      "tripId": "37822366-BT 26_27-43278",
      "headsign": "Chermside Interchange",
      "stopId": "CULT",
      "lat": -27.479915618896484,
      "lon": 153.0214385986328,
      "bearing": null,
      "speed": null,
      "status": "in_transit_to",
      "currentStopSequence": 4,
      "timestamp": 1784845685,
      "updatedAt": "2026-07-23T22:28:05.000Z"
    },
    {
      "id": "A7393ED51E387246BB3D6249943091E8_2187",
      "label": "2187",
      "routeId": "330",
      "mode": "bus",
      "tripId": "37822122-BT 26_27-43278",
      "headsign": "Queen Street station",
      "stopId": "RBWH",
      "lat": -27.448333740234375,
      "lon": 153.02908325195312,
      "bearing": null,
      "speed": null,
      "status": "in_transit_to",
      "currentStopSequence": 25,
      "timestamp": 1784845746,
      "updatedAt": "2026-07-23T22:29:06.000Z"
    },
    {
      "id": "A7393ED51E387246BB3D6249943091E8_2213",
      "label": "2213",
      "routeId": "330",
      "mode": "bus",
      "tripId": "37822125-BT 26_27-43278",
      "headsign": "Queen Street station",
      "stopId": null,
      "lat": -27.341720581054688,
      "lon": 153.04153442382812,
      "bearing": null,
      "speed": null,
      "status": "stopped_at",
      "currentStopSequence": 13,
      "timestamp": 1784845739,
      "updatedAt": "2026-07-23T22:28:59.000Z"
    },
    {
      "id": "A7393ED51E387246BB3D6249943091E8_2222",
      "label": "2222",
      "routeId": "330",
      "mode": "bus",
      "tripId": "37822123-BT 26_27-43278",
      "headsign": "Queen Street station",
      "stopId": "RBWH",
      "lat": -27.411972045898438,
      "lon": 153.03366088867188,
      "bearing": null,
      "speed": null,
      "status": "in_transit_to",
      "currentStopSequence": 24,
      "timestamp": 1784845706,
      "updatedAt": "2026-07-23T22:28:26.000Z"
    },
    {
      "id": "A7393ED51E387246BB3D6249943091E8_2223",
      "label": "2223",
      "routeId": "330",
      "mode": "bus",
      "tripId": "37822190-BT 26_27-43278",
      "headsign": "Bracken Ridge, Quinlan St",
      "stopId": "CHMS",
      "lat": -27.384498596191406,
      "lon": 153.03085327148438,
      "bearing": null,
      "speed": null,
      "status": "in_transit_to",
      "currentStopSequence": 8,
      "timestamp": 1784845741,
      "updatedAt": "2026-07-23T22:29:01.000Z"
    },
    {
      "id": "A7393ED51E387246BB3D6249943091E8_2228",
      "label": "2228",
      "routeId": "330",
      "mode": "bus",
      "tripId": "37822189-BT 26_27-43278",
      "headsign": "Bracken Ridge, Quinlan St",
      "stopId": null,
      "lat": -27.321666717529297,
      "lon": 153.02691650390625,
      "bearing": null,
      "speed": null,
      "status": "in_transit_to",
      "currentStopSequence": 23,
      "timestamp": 1784845758,
      "updatedAt": "2026-07-23T22:29:18.000Z"
    },
    {
      "id": "A7393ED51E387246BB3D6249943091E8_2253",
      "label": "2253",
      "routeId": "330",
      "mode": "bus",
      "tripId": "37822127-BT 26_27-43278",
      "headsign": "Queen Street station",
      "stopId": null,
      "lat": -27.31924819946289,
      "lon": 153.04136657714844,
      "bearing": null,
      "speed": null,
      "status": "in_transit_to",
      "currentStopSequence": 1,
      "timestamp": 1784845743,
      "updatedAt": "2026-07-23T22:29:03.000Z"
    },
    {
      "id": "A7393ED51E387246BB3D6249943091E8_2265",
      "label": "2265",
      "routeId": "330",
      "mode": "bus",
      "tripId": "37822188-BT 26_27-43278",
      "headsign": "Bracken Ridge, Quinlan St",
      "stopId": null,
      "lat": -27.314638137817383,
      "lon": 153.02830505371094,
      "bearing": null,
      "speed": null,
      "status": "in_transit_to",
      "currentStopSequence": 25,
      "timestamp": 1784845738,
      "updatedAt": "2026-07-23T22:28:58.000Z"
    },
    {
      "id": "A7393ED51E387246BB3D6249943091E8_2268",
      "label": "2268",
      "routeId": "330",
      "mode": "bus",
      "tripId": "37822124-BT 26_27-43278",
      "headsign": "Queen Street station",
      "stopId": null,
      "lat": -27.373998641967773,
      "lon": 153.0354461669922,
      "bearing": null,
      "speed": null,
      "status": "in_transit_to",
      "currentStopSequence": 21,
      "timestamp": 1784845749,
      "updatedAt": "2026-07-23T22:29:09.000Z"
    },
    {
      "id": "06EAC06E55F06AEC6418AEEBA19D5764_23",
      "label": "23",
      "routeId": "555",
      "mode": "bus",
      "tripId": "37982016-LCBS 26_27-43389",
      "headsign": "Brisbane City",
      "stopId": null,
      "lat": -27.494665145874023,
      "lon": 153.037353515625,
      "bearing": null,
      "speed": null,
      "status": "in_transit_to",
      "currentStopSequence": 10,
      "timestamp": 1784845762,
      "updatedAt": "2026-07-23T22:29:22.000Z"
    },
    {
      "id": "A7393ED51E387246BB3D6249943091E8_2304",
      "label": "2304",
      "routeId": "333",
      "mode": "bus",
      "tripId": "37822363-BT 26_27-43278",
      "headsign": "Chermside Interchange",
      "stopId": null,
      "lat": -27.399749755859375,
      "lon": 153.0314483642578,
      "bearing": null,
      "speed": null,
      "status": "in_transit_to",
      "currentStopSequence": 18,
      "timestamp": 1784845743,
      "updatedAt": "2026-07-23T22:29:03.000Z"
    },
    {
      "id": "A7393ED51E387246BB3D6249943091E8_2305",
      "label": "2305",
      "routeId": "330",
      "mode": "bus",
      "tripId": "37822192-BT 26_27-43278",
      "headsign": "Bracken Ridge, Quinlan St",
      "stopId": "QSTN",
      "lat": -27.470970153808594,
      "lon": 153.02357482910156,
      "bearing": null,
      "speed": null,
      "status": "stopped_at",
      "currentStopSequence": 1,
      "timestamp": 1784845734,
      "updatedAt": "2026-07-23T22:28:54.000Z"
    },
    {
      "id": "A7393ED51E387246BB3D6249943091E8_2308",
      "label": "2308",
      "routeId": "330",
      "mode": "bus",
      "tripId": "37822191-BT 26_27-43278",
      "headsign": "Bracken Ridge, Quinlan St",
      "stopId": "CHMS",
      "lat": -27.444276809692383,
      "lon": 153.0296173095703,
      "bearing": null,
      "speed": null,
      "status": "in_transit_to",
      "currentStopSequence": 7,
      "timestamp": 1784845736,
      "updatedAt": "2026-07-23T22:28:56.000Z"
    },
    {
      "id": "73DD7B678B530932DF783319BBF95E95_231",
      "label": "231",
      "routeId": "700",
      "mode": "bus",
      "tripId": "37582572-SBL 26_27-42893",
      "headsign": "Tweed Heads",
      "stopId": null,
      "lat": -27.993499755859375,
      "lon": 153.4280548095703,
      "bearing": null,
      "speed": null,
      "status": "stopped_at",
      "currentStopSequence": 17,
      "timestamp": 1784845754,
      "updatedAt": "2026-07-23T22:29:14.000Z"
    },
    {
      "id": "A7393ED51E387246BB3D6249943091E8_2339",
      "label": "2339",
      "routeId": "330",
      "mode": "bus",
      "tripId": "37822126-BT 26_27-43278",
      "headsign": "Queen Street station",
      "stopId": null,
      "lat": -27.32849884033203,
      "lon": 153.04161071777344,
      "bearing": null,
      "speed": null,
      "status": "in_transit_to",
      "currentStopSequence": 11,
      "timestamp": 1784845756,
      "updatedAt": "2026-07-23T22:29:16.000Z"
    },
    {
      "id": "A7393ED51E387246BB3D6249943091E8_2351",
      "label": "2351",
      "routeId": "333",
      "mode": "bus",
      "tripId": "37822284-BT 26_27-43278",
      "headsign": "Woolloongabba station",
      "stopId": "CHMS",
      "lat": -27.38455581665039,
      "lon": 153.03085327148438,
      "bearing": null,
      "speed": null,
      "status": "in_transit_to",
      "currentStopSequence": 2,
      "timestamp": 1784845736,
      "updatedAt": "2026-07-23T22:28:56.000Z"
    },
    {
      "id": "73DD7B678B530932DF783319BBF95E95_242",
      "label": "242",
      "routeId": "760",
      "mode": "bus",
      "tripId": "37584229-SBL 26_27-42893",
      "headsign": "Robina Town Centre",
      "stopId": null,
      "lat": -28.096805572509766,
      "lon": 153.39988708496094,
      "bearing": null,
      "speed": null,
      "status": "stopped_at",
      "currentStopSequence": 31,
      "timestamp": 1784845744,
      "updatedAt": "2026-07-23T22:29:04.000Z"
    },
    {
      "id": "73DD7B678B530932DF783319BBF95E95_248",
      "label": "248",
      "routeId": "700",
      "mode": "bus",
      "tripId": "37583698-SBL 26_27-42893",
      "headsign": "Broadbeach South station",
      "stopId": null,
      "lat": -28.135971069335938,
      "lon": 153.48707580566406,
      "bearing": null,
      "speed": null,
      "status": "in_transit_to",
      "currentStopSequence": 20,
      "timestamp": 1784845758,
      "updatedAt": "2026-07-23T22:29:18.000Z"
    },
    {
      "id": "73DD7B678B530932DF783319BBF95E95_252",
      "label": "252",
      "routeId": "760",
      "mode": "bus",
      "tripId": "37584224-SBL 26_27-42893",
      "headsign": "Robina Town Centre",
      "stopId": null,
      "lat": -28.135360717773438,
      "lon": 153.4785614013672,
      "bearing": null,
      "speed": null,
      "status": "in_transit_to",
      "currentStopSequence": 1,
      "timestamp": 1784845495,
      "updatedAt": "2026-07-23T22:24:55.000Z"
    },
    {
      "id": "73DD7B678B530932DF783319BBF95E95_253",
      "label": "253",
      "routeId": "700",
      "mode": "bus",
      "tripId": "37583841-SBL 26_27-42893",
      "headsign": "Broadbeach South station",
      "stopId": null,
      "lat": -28.17105484008789,
      "lon": 153.54330444335938,
      "bearing": null,
      "speed": null,
      "status": "stopped_at",
      "currentStopSequence": 1,
      "timestamp": 1784845758,
      "updatedAt": "2026-07-23T22:29:18.000Z"
    },
    {
      "id": "73DD7B678B530932DF783319BBF95E95_265",
      "label": "265",
      "routeId": "750",
      "mode": "bus",
      "tripId": "37581093-SBL 26_27-42893",
      "headsign": "Broadbeach South station",
      "stopId": null,
      "lat": -28.078081130981445,
      "lon": 153.41522216796875,
      "bearing": null,
      "speed": null,
      "status": "in_transit_to",
      "currentStopSequence": 9,
      "timestamp": 1784845759,
      "updatedAt": "2026-07-23T22:29:19.000Z"
    },
    {
      "id": "A7393ED51E387246BB3D6249943091E8_2804",
      "label": "2804",
      "routeId": "444",
      "mode": "bus",
      "tripId": "37814502-BT 26_27-43278",
      "headsign": "Moggill, Moggill Rd",
      "stopId": "CULT",
      "lat": -27.46502685546875,
      "lon": 153.0276641845703,
      "bearing": null,
      "speed": null,
      "status": "in_transit_to",
      "currentStopSequence": 1,
      "timestamp": 1784845748,
      "updatedAt": "2026-07-23T22:29:08.000Z"
    },
    {
      "id": "A7393ED51E387246BB3D6249943091E8_2805",
      "label": "2805",
      "routeId": "444",
      "mode": "bus",
      "tripId": "37814377-BT 26_27-43278",
      "headsign": "Moggill, Moggill Rd",
      "stopId": "CULT",
      "lat": -27.47144317626953,
      "lon": 153.01438903808594,
      "bearing": null,
      "speed": null,
      "status": "in_transit_to",
      "currentStopSequence": 1,
      "timestamp": 1784845743,
      "updatedAt": "2026-07-23T22:29:03.000Z"
    },
    {
      "id": "A7393ED51E387246BB3D6249943091E8_2821",
      "label": "2821",
      "routeId": "444",
      "mode": "bus",
      "tripId": "37813963-BT 26_27-43278",
      "headsign": "Moggill, Moggill Rd",
      "stopId": "INDR",
      "lat": -27.492944717407227,
      "lon": 152.9784698486328,
      "bearing": null,
      "speed": null,
      "status": "in_transit_to",
      "currentStopSequence": 11,
      "timestamp": 1784845757,
      "updatedAt": "2026-07-23T22:29:17.000Z"
    },
    {
      "id": "A7393ED51E387246BB3D6249943091E8_2827",
      "label": "2827",
      "routeId": "444",
      "mode": "bus",
      "tripId": "37813743-BT 26_27-43278",
      "headsign": "Queensland Theatre",
      "stopId": "TOOW",
      "lat": -27.490665435791016,
      "lon": 152.98536682128906,
      "bearing": null,
      "speed": null,
      "status": "in_transit_to",
      "currentStopSequence": 24,
      "timestamp": 1784845733,
      "updatedAt": "2026-07-23T22:28:53.000Z"
    },
    {
      "id": "A7393ED51E387246BB3D6249943091E8_2841",
      "label": "2841",
      "routeId": "444",
      "mode": "bus",
      "tripId": "37814175-BT 26_27-43278",
      "headsign": "Queensland Theatre",
      "stopId": null,
      "lat": -27.57044219970703,
      "lon": 152.8741912841797,
      "bearing": null,
      "speed": null,
      "status": "stopped_at",
      "currentStopSequence": 1,
      "timestamp": 1784845747,
      "updatedAt": "2026-07-23T22:29:07.000Z"
    },
    {
      "id": "A7393ED51E387246BB3D6249943091E8_2843",
      "label": "2843",
      "routeId": "444",
      "mode": "bus",
      "tripId": "37813793-BT 26_27-43278",
      "headsign": "Moggill, Moggill Rd",
      "stopId": null,
      "lat": -27.507749557495117,
      "lon": 152.93894958496094,
      "bearing": null,
      "speed": null,
      "status": "stopped_at",
      "currentStopSequence": 17,
      "timestamp": 1784845756,
      "updatedAt": "2026-07-23T22:29:16.000Z"
    },
    {
      "id": "A7393ED51E387246BB3D6249943091E8_2845",
      "label": "2845",
      "routeId": "444",
      "mode": "bus",
      "tripId": "37813608-BT 26_27-43278",
      "headsign": "Moggill, Moggill Rd",
      "stopId": null,
      "lat": -27.564722061157227,
      "lon": 152.87371826171875,
      "bearing": null,
      "speed": null,
      "status": "in_transit_to",
      "currentStopSequence": 29,
      "timestamp": 1784845737,
      "updatedAt": "2026-07-23T22:28:57.000Z"
    },
    {
      "id": "A7393ED51E387246BB3D6249943091E8_2850",
      "label": "2850",
      "routeId": "444",
      "mode": "bus",
      "tripId": "37813493-BT 26_27-43278",
      "headsign": "Queensland Theatre",
      "stopId": "ROMA",
      "lat": -27.469999313354492,
      "lon": 153.00897216796875,
      "bearing": null,
      "speed": null,
      "status": "in_transit_to",
      "currentStopSequence": 29,
      "timestamp": 1784845750,
      "updatedAt": "2026-07-23T22:29:10.000Z"
    },
    {
      "id": "A7393ED51E387246BB3D6249943091E8_2861",
      "label": "2861",
      "routeId": "333",
      "mode": "bus",
      "tripId": "37822290-BT 26_27-43278",
      "headsign": "Woolloongabba station",
      "stopId": "CHMS",
      "lat": -27.445415496826172,
      "lon": 153.02806091308594,
      "bearing": null,
      "speed": null,
      "status": "in_transit_to",
      "currentStopSequence": 1,
      "timestamp": 1784845754,
      "updatedAt": "2026-07-23T22:29:14.000Z"
    },
    {
      "id": "A7393ED51E387246BB3D6249943091E8_2895",
      "label": "2895",
      "routeId": "444",
      "mode": "bus",
      "tripId": "37814253-BT 26_27-43278",
      "headsign": "Moggill, Moggill Rd",
      "stopId": "CULT",
      "lat": -27.472026824951172,
      "lon": 153.0144500732422,
      "bearing": null,
      "speed": null,
      "status": "stopped_at",
      "currentStopSequence": 1,
      "timestamp": 1784845756,
      "updatedAt": "2026-07-23T22:29:16.000Z"
    },
    {
      "id": "A7393ED51E387246BB3D6249943091E8_2901",
      "label": "2901",
      "routeId": "444",
      "mode": "bus",
      "tripId": "37814082-BT 26_27-43278",
      "headsign": "Queensland Theatre",
      "stopId": null,
      "lat": -27.55472183227539,
      "lon": 152.88833618164062,
      "bearing": null,
      "speed": null,
      "status": "in_transit_to",
      "currentStopSequence": 10,
      "timestamp": 1784845751,
      "updatedAt": "2026-07-23T22:29:11.000Z"
    },
    {
      "id": "A7393ED51E387246BB3D6249943091E8_2911",
      "label": "2911",
      "routeId": "444",
      "mode": "bus",
      "tripId": "37814125-BT 26_27-43278",
      "headsign": "Moggill, Moggill Rd",
      "stopId": null,
      "lat": -27.465944290161133,
      "lon": 153.0145263671875,
      "bearing": null,
      "speed": null,
      "status": "in_transit_to",
      "currentStopSequence": 5,
      "timestamp": 1784845741,
      "updatedAt": "2026-07-23T22:29:01.000Z"
    },
    {
      "id": "73DD7B678B530932DF783319BBF95E95_327",
      "label": "327",
      "routeId": "700",
      "mode": "bus",
      "tripId": "37583563-SBL 26_27-42893",
      "headsign": "Broadbeach South station",
      "stopId": null,
      "lat": -28.17369270324707,
      "lon": 153.5433349609375,
      "bearing": null,
      "speed": null,
      "status": "in_transit_to",
      "currentStopSequence": 1,
      "timestamp": 1784845744,
      "updatedAt": "2026-07-23T22:29:04.000Z"
    },
    {
      "id": "73DD7B678B530932DF783319BBF95E95_334",
      "label": "334",
      "routeId": "700",
      "mode": "bus",
      "tripId": "37581608-SBL 26_27-42893",
      "headsign": "Tweed Heads",
      "stopId": null,
      "lat": -28.114776611328125,
      "lon": 153.46902465820312,
      "bearing": null,
      "speed": null,
      "status": "stopped_at",
      "currentStopSequence": 18,
      "timestamp": 1784845742,
      "updatedAt": "2026-07-23T22:29:02.000Z"
    },
    {
      "id": "06EAC06E55F06AEC6418AEEBA19D5764_36",
      "label": "36",
      "routeId": "560",
      "mode": "bus",
      "tripId": "37981586-LCBS 26_27-43389",
      "headsign": "Loganholme station",
      "stopId": null,
      "lat": -27.661582946777344,
      "lon": 153.0421600341797,
      "bearing": null,
      "speed": null,
      "status": "stopped_at",
      "currentStopSequence": 1,
      "timestamp": 1784845761,
      "updatedAt": "2026-07-23T22:29:21.000Z"
    },
    {
      "id": "73DD7B678B530932DF783319BBF95E95_365",
      "label": "365",
      "routeId": "760",
      "mode": "bus",
      "tripId": "37583876-SBL 26_27-42893",
      "headsign": "Tweed Heads",
      "stopId": null,
      "lat": -28.13197135925293,
      "lon": 153.48175048828125,
      "bearing": null,
      "speed": null,
      "status": "stopped_at",
      "currentStopSequence": 17,
      "timestamp": 1784845758,
      "updatedAt": "2026-07-23T22:29:18.000Z"
    },
    {
      "id": "73DD7B678B530932DF783319BBF95E95_366",
      "label": "366",
      "routeId": "777",
      "mode": "bus",
      "tripId": "37587050-SBL 26_27-42893",
      "headsign": "Broadbeach South station",
      "stopId": null,
      "lat": -28.16666603088379,
      "lon": 153.5134735107422,
      "bearing": null,
      "speed": null,
      "status": "in_transit_to",
      "currentStopSequence": 2,
      "timestamp": 1784845752,
      "updatedAt": "2026-07-23T22:29:12.000Z"
    },
    {
      "id": "73DD7B678B530932DF783319BBF95E95_383",
      "label": "383",
      "routeId": "700",
      "mode": "bus",
      "tripId": "37581461-SBL 26_27-42893",
      "headsign": "Broadbeach South station",
      "stopId": null,
      "lat": -28.11052703857422,
      "lon": 153.46658325195312,
      "bearing": null,
      "speed": null,
      "status": "stopped_at",
      "currentStopSequence": 28,
      "timestamp": 1784845751,
      "updatedAt": "2026-07-23T22:29:11.000Z"
    },
    {
      "id": "73DD7B678B530932DF783319BBF95E95_385",
      "label": "385",
      "routeId": "700",
      "mode": "bus",
      "tripId": "37581197-SBL 26_27-42893",
      "headsign": "Tweed Heads",
      "stopId": null,
      "lat": -28.16583251953125,
      "lon": 153.51986694335938,
      "bearing": null,
      "speed": null,
      "status": "stopped_at",
      "currentStopSequence": 35,
      "timestamp": 1784845738,
      "updatedAt": "2026-07-23T22:28:58.000Z"
    },
    {
      "id": "73DD7B678B530932DF783319BBF95E95_444",
      "label": "444",
      "routeId": "750",
      "mode": "bus",
      "tripId": "37581668-SBL 26_27-42893",
      "headsign": "Broadbeach South station",
      "stopId": "ROBINA",
      "lat": -28.071138381958008,
      "lon": 153.3772430419922,
      "bearing": null,
      "speed": null,
      "status": "in_transit_to",
      "currentStopSequence": 2,
      "timestamp": 1784845747,
      "updatedAt": "2026-07-23T22:29:07.000Z"
    },
    {
      "id": "73DD7B678B530932DF783319BBF95E95_446",
      "label": "446",
      "routeId": "750",
      "mode": "bus",
      "tripId": "37582366-SBL 26_27-42893",
      "headsign": "Robina station",
      "stopId": null,
      "lat": -28.080581665039062,
      "lon": 153.41021728515625,
      "bearing": null,
      "speed": null,
      "status": "in_transit_to",
      "currentStopSequence": 16,
      "timestamp": 1784845741,
      "updatedAt": "2026-07-23T22:29:01.000Z"
    },
    {
      "id": "73DD7B678B530932DF783319BBF95E95_471",
      "label": "471",
      "routeId": "700",
      "mode": "bus",
      "tripId": "37583598-SBL 26_27-42893",
      "headsign": "Tweed Heads",
      "stopId": "BURLEIGH",
      "lat": -28.088359832763672,
      "lon": 153.45147705078125,
      "bearing": null,
      "speed": null,
      "status": "in_transit_to",
      "currentStopSequence": 9,
      "timestamp": 1784845760,
      "updatedAt": "2026-07-23T22:29:20.000Z"
    },
    {
      "id": "A7393ED51E387246BB3D6249943091E8_5027",
      "label": "5027",
      "routeId": "222",
      "mode": "bus",
      "tripId": "37814115-BT 26_27-43278",
      "headsign": "Roma Street station",
      "stopId": "CARI",
      "lat": -27.50319480895996,
      "lon": 153.1032257080078,
      "bearing": null,
      "speed": null,
      "status": "stopped_at",
      "currentStopSequence": 1,
      "timestamp": 1784845732,
      "updatedAt": "2026-07-23T22:28:52.000Z"
    },
    {
      "id": "A7393ED51E387246BB3D6249943091E8_5032",
      "label": "5032",
      "routeId": "222",
      "mode": "bus",
      "tripId": "37813807-BT 26_27-43278",
      "headsign": "Carindale interchange",
      "stopId": "CARI",
      "lat": -27.50205421447754,
      "lon": 153.10353088378906,
      "bearing": null,
      "speed": null,
      "status": "in_transit_to",
      "currentStopSequence": 13,
      "timestamp": 1784845748,
      "updatedAt": "2026-07-23T22:29:08.000Z"
    },
    {
      "id": "A7393ED51E387246BB3D6249943091E8_5033",
      "label": "5033",
      "routeId": "222",
      "mode": "bus",
      "tripId": "37813899-BT 26_27-43278",
      "headsign": "Roma Street station",
      "stopId": "CULT",
      "lat": -27.474470138549805,
      "lon": 153.01771545410156,
      "bearing": null,
      "speed": null,
      "status": "in_transit_to",
      "currentStopSequence": 11,
      "timestamp": 1784845741,
      "updatedAt": "2026-07-23T22:29:01.000Z"
    },
    {
      "id": "A7393ED51E387246BB3D6249943091E8_5036",
      "label": "5036",
      "routeId": "169",
      "mode": "bus",
      "tripId": "37820675-BT 26_27-43278",
      "headsign": "UQ Lakes station",
      "stopId": "BURA",
      "lat": -27.505165100097656,
      "lon": 153.03941345214844,
      "bearing": null,
      "speed": null,
      "status": "in_transit_to",
      "currentStopSequence": 6,
      "timestamp": 1784845737,
      "updatedAt": "2026-07-23T22:28:57.000Z"
    },
    {
      "id": "A7393ED51E387246BB3D6249943091E8_5051",
      "label": "5051",
      "routeId": "169",
      "mode": "bus",
      "tripId": "37820743-BT 26_27-43278",
      "headsign": "Eight Mile Plains station",
      "stopId": null,
      "lat": -27.54658317565918,
      "lon": 153.0644989013672,
      "bearing": null,
      "speed": null,
      "status": "stopped_at",
      "currentStopSequence": 8,
      "timestamp": 1784845732,
      "updatedAt": "2026-07-23T22:28:52.000Z"
    },
    {
      "id": "A7393ED51E387246BB3D6249943091E8_5055",
      "label": "5055",
      "routeId": "169",
      "mode": "bus",
      "tripId": "37820677-BT 26_27-43278",
      "headsign": "UQ Lakes station",
      "stopId": "GARD",
      "lat": -27.56399917602539,
      "lon": 153.081298828125,
      "bearing": null,
      "speed": null,
      "status": "stopped_at",
      "currentStopSequence": 2,
      "timestamp": 1784845743,
      "updatedAt": "2026-07-23T22:29:03.000Z"
    },
    {
      "id": "A7393ED51E387246BB3D6249943091E8_5070",
      "label": "5070",
      "routeId": "222",
      "mode": "bus",
      "tripId": "37814263-BT 26_27-43278",
      "headsign": "Carindale interchange",
      "stopId": "ROMA",
      "lat": -27.46413803100586,
      "lon": 153.0159454345703,
      "bearing": null,
      "speed": null,
      "status": "in_transit_to",
      "currentStopSequence": 1,
      "timestamp": 1784845742,
      "updatedAt": "2026-07-23T22:29:02.000Z"
    },
    {
      "id": "A7393ED51E387246BB3D6249943091E8_5071",
      "label": "5071",
      "routeId": "222",
      "mode": "bus",
      "tripId": "37814596-BT 26_27-43278",
      "headsign": "Roma Street station",
      "stopId": "CARI",
      "lat": -27.50208282470703,
      "lon": 153.10350036621094,
      "bearing": null,
      "speed": null,
      "status": "in_transit_to",
      "currentStopSequence": 1,
      "timestamp": 1784845730,
      "updatedAt": "2026-07-23T22:28:50.000Z"
    },
    {
      "id": "A7393ED51E387246BB3D6249943091E8_5077",
      "label": "5077",
      "routeId": "222",
      "mode": "bus",
      "tripId": "37814514-BT 26_27-43278",
      "headsign": "Carindale interchange",
      "stopId": "ROMA",
      "lat": -27.456666946411133,
      "lon": 153.01844787597656,
      "bearing": null,
      "speed": null,
      "status": "in_transit_to",
      "currentStopSequence": 1,
      "timestamp": 1784845749,
      "updatedAt": "2026-07-23T22:29:09.000Z"
    },
    {
      "id": "A7393ED51E387246BB3D6249943091E8_5085",
      "label": "5085",
      "routeId": "222",
      "mode": "bus",
      "tripId": "37820906-BT 26_27-43278",
      "headsign": "Roma Street station",
      "stopId": null,
      "lat": -27.495277404785156,
      "lon": 153.05780029296875,
      "bearing": null,
      "speed": null,
      "status": "in_transit_to",
      "currentStopSequence": 6,
      "timestamp": 1784845742,
      "updatedAt": "2026-07-23T22:29:02.000Z"
    },
    {
      "id": "A7393ED51E387246BB3D6249943091E8_5090",
      "label": "5090",
      "routeId": "222",
      "mode": "bus",
      "tripId": "37814208-BT 26_27-43278",
      "headsign": "Roma Street station",
      "stopId": "CARI",
      "lat": -27.50519371032715,
      "lon": 153.1026611328125,
      "bearing": null,
      "speed": null,
      "status": "in_transit_to",
      "currentStopSequence": 1,
      "timestamp": 1784845731,
      "updatedAt": "2026-07-23T22:28:51.000Z"
    },
    {
      "id": "A7393ED51E387246BB3D6249943091E8_5092",
      "label": "5092",
      "routeId": "222",
      "mode": "bus",
      "tripId": "37814013-BT 26_27-43278",
      "headsign": "Roma Street station",
      "stopId": "BURA",
      "lat": -27.497360229492188,
      "lon": 153.03958129882812,
      "bearing": null,
      "speed": null,
      "status": "stopped_at",
      "currentStopSequence": 8,
      "timestamp": 1784845747,
      "updatedAt": "2026-07-23T22:29:07.000Z"
    },
    {
      "id": "A7393ED51E387246BB3D6249943091E8_5123",
      "label": "5123",
      "routeId": "222",
      "mode": "bus",
      "tripId": "37820907-BT 26_27-43278",
      "headsign": "Roma Street station",
      "stopId": null,
      "lat": -27.49313735961914,
      "lon": 153.0780487060547,
      "bearing": null,
      "speed": null,
      "status": "in_transit_to",
      "currentStopSequence": 3,
      "timestamp": 1784845750,
      "updatedAt": "2026-07-23T22:29:10.000Z"
    },
    {
      "id": "A7393ED51E387246BB3D6249943091E8_5125",
      "label": "5125",
      "routeId": "222",
      "mode": "bus",
      "tripId": "37813974-BT 26_27-43278",
      "headsign": "Carindale interchange",
      "stopId": null,
      "lat": -27.498638153076172,
      "lon": 153.0504150390625,
      "bearing": null,
      "speed": null,
      "status": "in_transit_to",
      "currentStopSequence": 9,
      "timestamp": 1784845755,
      "updatedAt": "2026-07-23T22:29:15.000Z"
    },
    {
      "id": "A7393ED51E387246BB3D6249943091E8_5138",
      "label": "5138",
      "routeId": "169",
      "mode": "bus",
      "tripId": "37820679-BT 26_27-43278",
      "headsign": "UQ Lakes station",
      "stopId": "EMPS",
      "lat": -27.573360443115234,
      "lon": 153.09686279296875,
      "bearing": null,
      "speed": null,
      "status": "in_transit_to",
      "currentStopSequence": 1,
      "timestamp": 1784845737,
      "updatedAt": "2026-07-23T22:28:57.000Z"
    },
    {
      "id": "A7393ED51E387246BB3D6249943091E8_5153",
      "label": "5153",
      "routeId": "169",
      "mode": "bus",
      "tripId": "37820678-BT 26_27-43278",
      "headsign": "UQ Lakes station",
      "stopId": "EMPS",
      "lat": -27.578998565673828,
      "lon": 153.1022491455078,
      "bearing": null,
      "speed": null,
      "status": "stopped_at",
      "currentStopSequence": 1,
      "timestamp": 1784845745,
      "updatedAt": "2026-07-23T22:29:05.000Z"
    },
    {
      "id": "06EAC06E55F06AEC6418AEEBA19D5764_53",
      "label": "53",
      "routeId": "560",
      "mode": "bus",
      "tripId": "37981420-LCBS 26_27-43389",
      "headsign": "Browns Plains",
      "stopId": "LGHM",
      "lat": -27.660694122314453,
      "lon": 153.17388916015625,
      "bearing": null,
      "speed": null,
      "status": "stopped_at",
      "currentStopSequence": 1,
      "timestamp": 1784844031,
      "updatedAt": "2026-07-23T22:00:31.000Z"
    },
    {
      "id": "06EAC06E55F06AEC6418AEEBA19D5764_555",
      "label": "555",
      "routeId": "555",
      "mode": "bus",
      "tripId": "37981009-LCBS 26_27-43389",
      "headsign": "Loganholme station",
      "stopId": null,
      "lat": -27.48041534423828,
      "lon": 153.02174377441406,
      "bearing": null,
      "speed": null,
      "status": "in_transit_to",
      "currentStopSequence": 5,
      "timestamp": 1784845765,
      "updatedAt": "2026-07-23T22:29:25.000Z"
    },
    {
      "id": "06EAC06E55F06AEC6418AEEBA19D5764_556",
      "label": "556",
      "routeId": "555",
      "mode": "bus",
      "tripId": "37981019-LCBS 26_27-43389",
      "headsign": "Loganholme station",
      "stopId": "SPRW",
      "lat": -27.598276138305664,
      "lon": 153.1146697998047,
      "bearing": null,
      "speed": null,
      "status": "in_transit_to",
      "currentStopSequence": 14,
      "timestamp": 1784845762,
      "updatedAt": "2026-07-23T22:29:22.000Z"
    },
    {
      "id": "06EAC06E55F06AEC6418AEEBA19D5764_63",
      "label": "63",
      "routeId": "555",
      "mode": "bus",
      "tripId": "37981924-LCBS 26_27-43389",
      "headsign": "Brisbane City",
      "stopId": "SPRW",
      "lat": -27.615026473999023,
      "lon": 153.125,
      "bearing": null,
      "speed": null,
      "status": "stopped_at",
      "currentStopSequence": 2,
      "timestamp": 1784845756,
      "updatedAt": "2026-07-23T22:29:16.000Z"
    },
    {
      "id": "06EAC06E55F06AEC6418AEEBA19D5764_70",
      "label": "70",
      "routeId": "555",
      "mode": "bus",
      "tripId": "37982035-LCBS 26_27-43389",
      "headsign": "Brisbane City",
      "stopId": "GARD",
      "lat": -27.56769371032715,
      "lon": 153.08663940429688,
      "bearing": null,
      "speed": null,
      "status": "in_transit_to",
      "currentStopSequence": 5,
      "timestamp": 1784845756,
      "updatedAt": "2026-07-23T22:29:16.000Z"
    },
    {
      "id": "A7393ED51E387246BB3D6249943091E8_7142",
      "label": "7142",
      "routeId": "333",
      "mode": "bus",
      "tripId": "37822364-BT 26_27-43278",
      "headsign": "Chermside Interchange",
      "stopId": null,
      "lat": -27.441720962524414,
      "lon": 153.03115844726562,
      "bearing": null,
      "speed": null,
      "status": "in_transit_to",
      "currentStopSequence": 11,
      "timestamp": 1784845739,
      "updatedAt": "2026-07-23T22:28:59.000Z"
    },
    {
      "id": "A7393ED51E387246BB3D6249943091E8_7169",
      "label": "7169",
      "routeId": "333",
      "mode": "bus",
      "tripId": "37822287-BT 26_27-43278",
      "headsign": "Woolloongabba station",
      "stopId": "CHMS",
      "lat": -27.473777770996094,
      "lon": 153.02389526367188,
      "bearing": null,
      "speed": null,
      "status": "in_transit_to",
      "currentStopSequence": 1,
      "timestamp": 1784845742,
      "updatedAt": "2026-07-23T22:29:02.000Z"
    },
    {
      "id": "A7393ED51E387246BB3D6249943091E8_7180",
      "label": "7180",
      "routeId": "333",
      "mode": "bus",
      "tripId": "37822283-BT 26_27-43278",
      "headsign": "Woolloongabba station",
      "stopId": null,
      "lat": -27.412166595458984,
      "lon": 153.0338897705078,
      "bearing": null,
      "speed": null,
      "status": "in_transit_to",
      "currentStopSequence": 7,
      "timestamp": 1784845751,
      "updatedAt": "2026-07-23T22:29:11.000Z"
    },
    {
      "id": "A7393ED51E387246BB3D6249943091E8_7191",
      "label": "7191",
      "routeId": "333",
      "mode": "bus",
      "tripId": "37822279-BT 26_27-43278",
      "headsign": "Woolloongabba station",
      "stopId": "KING",
      "lat": -27.466720581054688,
      "lon": 153.02166748046875,
      "bearing": null,
      "speed": null,
      "status": "in_transit_to",
      "currentStopSequence": 16,
      "timestamp": 1784845750,
      "updatedAt": "2026-07-23T22:29:10.000Z"
    },
    {
      "id": "A7393ED51E387246BB3D6249943091E8_7201",
      "label": "7201",
      "routeId": "333",
      "mode": "bus",
      "tripId": "37822280-BT 26_27-43278",
      "headsign": "Woolloongabba station",
      "stopId": null,
      "lat": -27.400554656982422,
      "lon": 153.03163146972656,
      "bearing": null,
      "speed": null,
      "status": "in_transit_to",
      "currentStopSequence": 5,
      "timestamp": 1784845747,
      "updatedAt": "2026-07-23T22:29:07.000Z"
    },
    {
      "id": "A7393ED51E387246BB3D6249943091E8_7216",
      "label": "7216",
      "routeId": "333",
      "mode": "bus",
      "tripId": "37822282-BT 26_27-43278",
      "headsign": "Woolloongabba station",
      "stopId": null,
      "lat": -27.412193298339844,
      "lon": 153.03392028808594,
      "bearing": null,
      "speed": null,
      "status": "in_transit_to",
      "currentStopSequence": 7,
      "timestamp": 1784845734,
      "updatedAt": "2026-07-23T22:28:54.000Z"
    },
    {
      "id": "06EAC06E55F06AEC6418AEEBA19D5764_77",
      "label": "77",
      "routeId": "560",
      "mode": "bus",
      "tripId": "37981513-LCBS 26_27-43389",
      "headsign": "Loganholme station",
      "stopId": null,
      "lat": -27.655860900878906,
      "lon": 153.1669464111328,
      "bearing": null,
      "speed": null,
      "status": "in_transit_to",
      "currentStopSequence": 57,
      "timestamp": 1784845760,
      "updatedAt": "2026-07-23T22:29:20.000Z"
    },
    {
      "id": "73DD7B678B530932DF783319BBF95E95_790",
      "label": "790",
      "routeId": "750",
      "mode": "bus",
      "tripId": "37585307-SBL 26_27-42893",
      "headsign": "Broadbeach South station",
      "stopId": null,
      "lat": -28.070831298828125,
      "lon": 153.37869262695312,
      "bearing": null,
      "speed": null,
      "status": "stopped_at",
      "currentStopSequence": 1,
      "timestamp": 1784845741,
      "updatedAt": "2026-07-23T22:29:01.000Z"
    },
    {
      "id": "73DD7B678B530932DF783319BBF95E95_924",
      "label": "924",
      "routeId": "700",
      "mode": "bus",
      "tripId": "37583460-SBL 26_27-42893",
      "headsign": "Tweed Heads",
      "stopId": "BBS",
      "lat": -28.03558349609375,
      "lon": 153.43092346191406,
      "bearing": null,
      "speed": null,
      "status": "stopped_at",
      "currentStopSequence": 1,
      "timestamp": 1784845758,
      "updatedAt": "2026-07-23T22:29:18.000Z"
    },
    {
      "id": "73DD7B678B530932DF783319BBF95E95_927",
      "label": "927",
      "routeId": "760",
      "mode": "bus",
      "tripId": "37583490-SBL 26_27-42893",
      "headsign": "Tweed Heads",
      "stopId": null,
      "lat": -28.09699821472168,
      "lon": 153.40016174316406,
      "bearing": null,
      "speed": null,
      "status": "stopped_at",
      "currentStopSequence": 6,
      "timestamp": 1784845740,
      "updatedAt": "2026-07-23T22:29:00.000Z"
    },
    {
      "id": "73DD7B678B530932DF783319BBF95E95_928",
      "label": "928",
      "routeId": "700",
      "mode": "bus",
      "tripId": "37584248-SBL 26_27-42893",
      "headsign": "Broadbeach South station",
      "stopId": null,
      "lat": -28.073442459106445,
      "lon": 153.44424438476562,
      "bearing": null,
      "speed": null,
      "status": "in_transit_to",
      "currentStopSequence": 38,
      "timestamp": 1784845736,
      "updatedAt": "2026-07-23T22:28:56.000Z"
    },
    {
      "id": "73DD7B678B530932DF783319BBF95E95_931",
      "label": "931",
      "routeId": "760",
      "mode": "bus",
      "tripId": "37583553-SBL 26_27-42893",
      "headsign": "Tweed Heads",
      "stopId": "ROBINA",
      "lat": -28.070859909057617,
      "lon": 153.37754821777344,
      "bearing": null,
      "speed": null,
      "status": "in_transit_to",
      "currentStopSequence": 1,
      "timestamp": 1784844523,
      "updatedAt": "2026-07-23T22:08:43.000Z"
    },
    {
      "id": "73DD7B678B530932DF783319BBF95E95_955",
      "label": "955",
      "routeId": "760",
      "mode": "bus",
      "tripId": "37581018-SBL 26_27-42893",
      "headsign": "Robina Town Centre",
      "stopId": null,
      "lat": -28.13599967956543,
      "lon": 153.48692321777344,
      "bearing": null,
      "speed": null,
      "status": "in_transit_to",
      "currentStopSequence": 20,
      "timestamp": 1784845743,
      "updatedAt": "2026-07-23T22:29:03.000Z"
    },
    {
      "id": "73DD7B678B530932DF783319BBF95E95_979",
      "label": "979",
      "routeId": "700",
      "mode": "bus",
      "tripId": "37586389-SBL 26_27-42893",
      "headsign": "Tweed Heads",
      "stopId": null,
      "lat": -28.05958366394043,
      "lon": 153.43788146972656,
      "bearing": null,
      "speed": null,
      "status": "stopped_at",
      "currentStopSequence": 4,
      "timestamp": 1784845739,
      "updatedAt": "2026-07-23T22:28:59.000Z"
    }
  ]
}