{
  "meta": {
    "generatedAt": "2026-07-22T03:44:15.577Z",
    "source": "build-live-from-gtfsrt.mjs",
    "feedFormat": "protobuf",
    "sourcePaths": [
      "./raw/live/vehicle-positions.pb",
      "./raw/live/tram-vehicle-positions.pb"
    ],
    "stats": {
      "rows": 1031,
      "mappedRows": 88,
      "unmappedRoutes": 943,
      "vehicleCount": 88
    }
  },
  "vehicles": [
    {
      "id": "73DD7B678B530932DF783319BBF95E95_1008",
      "label": "1008",
      "routeId": "700",
      "mode": "bus",
      "tripId": "37582017-SBL 26_27-42893",
      "headsign": "Tweed Heads",
      "stopId": null,
      "lat": -28.120637893676758,
      "lon": 153.47250366210938,
      "bearing": null,
      "speed": null,
      "status": "in_transit_to",
      "currentStopSequence": 21,
      "timestamp": 1784691815,
      "updatedAt": "2026-07-22T03:43:35.000Z"
    },
    {
      "id": "73DD7B678B530932DF783319BBF95E95_101",
      "label": "101",
      "routeId": "777",
      "mode": "bus",
      "tripId": "37586973-SBL 26_27-42893",
      "headsign": "Broadbeach South station",
      "stopId": null,
      "lat": -28.14705467224121,
      "lon": 153.47569274902344,
      "bearing": null,
      "speed": null,
      "status": "in_transit_to",
      "currentStopSequence": 1,
      "timestamp": 1784691817,
      "updatedAt": "2026-07-22T03:43:37.000Z"
    },
    {
      "id": "73DD7B678B530932DF783319BBF95E95_102",
      "label": "102",
      "routeId": "777",
      "mode": "bus",
      "tripId": "37586980-SBL 26_27-42893",
      "headsign": "Broadbeach South station",
      "stopId": null,
      "lat": -28.16669273376465,
      "lon": 153.51344299316406,
      "bearing": null,
      "speed": null,
      "status": "stopped_at",
      "currentStopSequence": 1,
      "timestamp": 1784691828,
      "updatedAt": "2026-07-22T03:43:48.000Z"
    },
    {
      "id": "73DD7B678B530932DF783319BBF95E95_103",
      "label": "103",
      "routeId": "777",
      "mode": "bus",
      "tripId": "37586995-SBL 26_27-42893",
      "headsign": "Broadbeach South station",
      "stopId": null,
      "lat": -28.065637588500977,
      "lon": 153.43902587890625,
      "bearing": null,
      "speed": null,
      "status": "in_transit_to",
      "currentStopSequence": 9,
      "timestamp": 1784691807,
      "updatedAt": "2026-07-22T03:43:27.000Z"
    },
    {
      "id": "73DD7B678B530932DF783319BBF95E95_104",
      "label": "104",
      "routeId": "777",
      "mode": "bus",
      "tripId": "37587023-SBL 26_27-42893",
      "headsign": "Gold Coast Airport",
      "stopId": null,
      "lat": -28.130220413208008,
      "lon": 153.4794921875,
      "bearing": null,
      "speed": null,
      "status": "in_transit_to",
      "currentStopSequence": 13,
      "timestamp": 1784691825,
      "updatedAt": "2026-07-22T03:43:45.000Z"
    },
    {
      "id": "73DD7B678B530932DF783319BBF95E95_105",
      "label": "105",
      "routeId": "777",
      "mode": "bus",
      "tripId": "37586983-SBL 26_27-42893",
      "headsign": "Gold Coast Airport",
      "stopId": null,
      "lat": -28.059083938598633,
      "lon": 153.43817138671875,
      "bearing": null,
      "speed": null,
      "status": "in_transit_to",
      "currentStopSequence": 4,
      "timestamp": 1784691829,
      "updatedAt": "2026-07-22T03:43:49.000Z"
    },
    {
      "id": "73DD7B678B530932DF783319BBF95E95_106",
      "label": "106",
      "routeId": "777",
      "mode": "bus",
      "tripId": "37587024-SBL 26_27-42893",
      "headsign": "Broadbeach South station",
      "stopId": null,
      "lat": -28.116554260253906,
      "lon": 153.46986389160156,
      "bearing": null,
      "speed": null,
      "status": "in_transit_to",
      "currentStopSequence": 3,
      "timestamp": 1784691819,
      "updatedAt": "2026-07-22T03:43:39.000Z"
    },
    {
      "id": "06EAC06E55F06AEC6418AEEBA19D5764_11",
      "label": "11",
      "routeId": "555",
      "mode": "bus",
      "tripId": "37982042-LCBS 26_27-43389",
      "headsign": "Loganholme station",
      "stopId": null,
      "lat": -27.545387268066406,
      "lon": 153.06317138671875,
      "bearing": null,
      "speed": null,
      "status": "in_transit_to",
      "currentStopSequence": 10,
      "timestamp": 1784691829,
      "updatedAt": "2026-07-22T03:43:49.000Z"
    },
    {
      "id": "06EAC06E55F06AEC6418AEEBA19D5764_132",
      "label": "132",
      "routeId": "555",
      "mode": "bus",
      "tripId": "37982099-LCBS 26_27-43389",
      "headsign": "Loganholme station",
      "stopId": "LGHM",
      "lat": -27.660860061645508,
      "lon": 153.173583984375,
      "bearing": null,
      "speed": null,
      "status": "in_transit_to",
      "currentStopSequence": 15,
      "timestamp": 1784691825,
      "updatedAt": "2026-07-22T03:43:45.000Z"
    },
    {
      "id": "06EAC06E55F06AEC6418AEEBA19D5764_15",
      "label": "15",
      "routeId": "555",
      "mode": "bus",
      "tripId": "37982686-LCBS 26_27-43389",
      "headsign": "Brisbane City",
      "stopId": "LGHM",
      "lat": -27.660276412963867,
      "lon": 153.17352294921875,
      "bearing": null,
      "speed": null,
      "status": "stopped_at",
      "currentStopSequence": 1,
      "timestamp": 1784691824,
      "updatedAt": "2026-07-22T03:43:44.000Z"
    },
    {
      "id": "06EAC06E55F06AEC6418AEEBA19D5764_16",
      "label": "16",
      "routeId": "555",
      "mode": "bus",
      "tripId": "37982698-LCBS 26_27-43389",
      "headsign": "Brisbane City",
      "stopId": "LGHM",
      "lat": -27.68260955810547,
      "lon": 153.17247009277344,
      "bearing": null,
      "speed": null,
      "status": "in_transit_to",
      "currentStopSequence": 1,
      "timestamp": 1784691812,
      "updatedAt": "2026-07-22T03:43:32.000Z"
    },
    {
      "id": "A7393ED51E387246BB3D6249943091E8_1635",
      "label": "1635",
      "routeId": "169",
      "mode": "bus",
      "tripId": "37820763-BT 26_27-43278",
      "headsign": "Eight Mile Plains station",
      "stopId": null,
      "lat": -27.510637283325195,
      "lon": 153.0400848388672,
      "bearing": null,
      "speed": null,
      "status": "stopped_at",
      "currentStopSequence": 6,
      "timestamp": 1784691831,
      "updatedAt": "2026-07-22T03:43:51.000Z"
    },
    {
      "id": "A7393ED51E387246BB3D6249943091E8_1638",
      "label": "1638",
      "routeId": "169",
      "mode": "bus",
      "tripId": "37820764-BT 26_27-43278",
      "headsign": "Eight Mile Plains station",
      "stopId": "UQLA",
      "lat": -27.497804641723633,
      "lon": 153.01791381835938,
      "bearing": null,
      "speed": null,
      "status": "stopped_at",
      "currentStopSequence": 1,
      "timestamp": 1784691810,
      "updatedAt": "2026-07-22T03:43:30.000Z"
    },
    {
      "id": "A7393ED51E387246BB3D6249943091E8_1892",
      "label": "1892",
      "routeId": "333",
      "mode": "bus",
      "tripId": "37822391-BT 26_27-43278",
      "headsign": "Chermside Interchange",
      "stopId": "ROMA",
      "lat": -27.46619415283203,
      "lon": 153.02035522460938,
      "bearing": null,
      "speed": null,
      "status": "in_transit_to",
      "currentStopSequence": 6,
      "timestamp": 1784691831,
      "updatedAt": "2026-07-22T03:43:51.000Z"
    },
    {
      "id": "A7393ED51E387246BB3D6249943091E8_2117",
      "label": "2117",
      "routeId": "333",
      "mode": "bus",
      "tripId": "37822390-BT 26_27-43278",
      "headsign": "Chermside Interchange",
      "stopId": null,
      "lat": -27.4381103515625,
      "lon": 153.0308380126953,
      "bearing": null,
      "speed": null,
      "status": "in_transit_to",
      "currentStopSequence": 11,
      "timestamp": 1784691826,
      "updatedAt": "2026-07-22T03:43:46.000Z"
    },
    {
      "id": "A7393ED51E387246BB3D6249943091E8_2118",
      "label": "2118",
      "routeId": "330",
      "mode": "bus",
      "tripId": "37822210-BT 26_27-43278",
      "headsign": "Bracken Ridge, Quinlan St",
      "stopId": null,
      "lat": -27.331581115722656,
      "lon": 153.0423126220703,
      "bearing": null,
      "speed": null,
      "status": "in_transit_to",
      "currentStopSequence": 19,
      "timestamp": 1784691818,
      "updatedAt": "2026-07-22T03:43:38.000Z"
    },
    {
      "id": "A7393ED51E387246BB3D6249943091E8_2120",
      "label": "2120",
      "routeId": "333",
      "mode": "bus",
      "tripId": "37822392-BT 26_27-43278",
      "headsign": "Chermside Interchange",
      "stopId": null,
      "lat": -27.47169303894043,
      "lon": 153.0762176513672,
      "bearing": null,
      "speed": null,
      "status": "in_transit_to",
      "currentStopSequence": 1,
      "timestamp": 1784691816,
      "updatedAt": "2026-07-22T03:43:36.000Z"
    },
    {
      "id": "A7393ED51E387246BB3D6249943091E8_2152",
      "label": "2152",
      "routeId": "330",
      "mode": "bus",
      "tripId": "37822147-BT 26_27-43278",
      "headsign": "Queen Street station",
      "stopId": null,
      "lat": -27.358333587646484,
      "lon": 153.03846740722656,
      "bearing": null,
      "speed": null,
      "status": "stopped_at",
      "currentStopSequence": 18,
      "timestamp": 1784691828,
      "updatedAt": "2026-07-22T03:43:48.000Z"
    },
    {
      "id": "A7393ED51E387246BB3D6249943091E8_2182",
      "label": "2182",
      "routeId": "333",
      "mode": "bus",
      "tripId": "37822309-BT 26_27-43278",
      "headsign": "Woolloongabba station",
      "stopId": "CHMS",
      "lat": -27.385805130004883,
      "lon": 153.0317840576172,
      "bearing": null,
      "speed": null,
      "status": "stopped_at",
      "currentStopSequence": 1,
      "timestamp": 1784691828,
      "updatedAt": "2026-07-22T03:43:48.000Z"
    },
    {
      "id": "A7393ED51E387246BB3D6249943091E8_2183",
      "label": "2183",
      "routeId": "333",
      "mode": "bus",
      "tripId": "37822310-BT 26_27-43278",
      "headsign": "Woolloongabba station",
      "stopId": "CHMS",
      "lat": -27.366527557373047,
      "lon": 153.06138610839844,
      "bearing": null,
      "speed": null,
      "status": "in_transit_to",
      "currentStopSequence": 1,
      "timestamp": 1784691809,
      "updatedAt": "2026-07-22T03:43:29.000Z"
    },
    {
      "id": "A7393ED51E387246BB3D6249943091E8_2198",
      "label": "2198",
      "routeId": "333",
      "mode": "bus",
      "tripId": "37822389-BT 26_27-43278",
      "headsign": "Chermside Interchange",
      "stopId": "CHMS",
      "lat": -27.385555267333984,
      "lon": 153.03179931640625,
      "bearing": null,
      "speed": null,
      "status": "stopped_at",
      "currentStopSequence": 19,
      "timestamp": 1784691813,
      "updatedAt": "2026-07-22T03:43:33.000Z"
    },
    {
      "id": "A7393ED51E387246BB3D6249943091E8_2207",
      "label": "2207",
      "routeId": "330",
      "mode": "bus",
      "tripId": "37822215-BT 26_27-43278",
      "headsign": "Bracken Ridge, Quinlan St",
      "stopId": "QSTN",
      "lat": -27.450777053833008,
      "lon": 153.0269775390625,
      "bearing": null,
      "speed": null,
      "status": "in_transit_to",
      "currentStopSequence": 1,
      "timestamp": 1784691830,
      "updatedAt": "2026-07-22T03:43:50.000Z"
    },
    {
      "id": "A7393ED51E387246BB3D6249943091E8_2211",
      "label": "2211",
      "routeId": "330",
      "mode": "bus",
      "tripId": "37822150-BT 26_27-43278",
      "headsign": "Queen Street station",
      "stopId": null,
      "lat": -27.365222930908203,
      "lon": 153.05978393554688,
      "bearing": null,
      "speed": null,
      "status": "in_transit_to",
      "currentStopSequence": 1,
      "timestamp": 1784691816,
      "updatedAt": "2026-07-22T03:43:36.000Z"
    },
    {
      "id": "A7393ED51E387246BB3D6249943091E8_2216",
      "label": "2216",
      "routeId": "330",
      "mode": "bus",
      "tripId": "37822213-BT 26_27-43278",
      "headsign": "Bracken Ridge, Quinlan St",
      "stopId": "QSTN",
      "lat": -27.470970153808594,
      "lon": 153.02357482910156,
      "bearing": null,
      "speed": null,
      "status": "stopped_at",
      "currentStopSequence": 1,
      "timestamp": 1784691806,
      "updatedAt": "2026-07-22T03:43:26.000Z"
    },
    {
      "id": "A7393ED51E387246BB3D6249943091E8_2241",
      "label": "2241",
      "routeId": "330",
      "mode": "bus",
      "tripId": "37822146-BT 26_27-43278",
      "headsign": "Queen Street station",
      "stopId": "RBWH",
      "lat": -27.401527404785156,
      "lon": 153.031494140625,
      "bearing": null,
      "speed": null,
      "status": "in_transit_to",
      "currentStopSequence": 24,
      "timestamp": 1784691827,
      "updatedAt": "2026-07-22T03:43:47.000Z"
    },
    {
      "id": "A7393ED51E387246BB3D6249943091E8_2251",
      "label": "2251",
      "routeId": "330",
      "mode": "bus",
      "tripId": "37822145-BT 26_27-43278",
      "headsign": "Queen Street station",
      "stopId": "QSTN",
      "lat": -27.46616554260254,
      "lon": 153.02049255371094,
      "bearing": null,
      "speed": null,
      "status": "in_transit_to",
      "currentStopSequence": 29,
      "timestamp": 1784691830,
      "updatedAt": "2026-07-22T03:43:50.000Z"
    },
    {
      "id": "A7393ED51E387246BB3D6249943091E8_2260",
      "label": "2260",
      "routeId": "333",
      "mode": "bus",
      "tripId": "37822308-BT 26_27-43278",
      "headsign": "Woolloongabba station",
      "stopId": null,
      "lat": -27.414915084838867,
      "lon": 153.03533935546875,
      "bearing": null,
      "speed": null,
      "status": "stopped_at",
      "currentStopSequence": 7,
      "timestamp": 1784691818,
      "updatedAt": "2026-07-22T03:43:38.000Z"
    },
    {
      "id": "73DD7B678B530932DF783319BBF95E95_230",
      "label": "230",
      "routeId": "700",
      "mode": "bus",
      "tripId": "37586626-SBL 26_27-42893",
      "headsign": "Broadbeach South station",
      "stopId": null,
      "lat": -28.068443298339844,
      "lon": 153.4413604736328,
      "bearing": null,
      "speed": null,
      "status": "stopped_at",
      "currentStopSequence": 38,
      "timestamp": 1784691803,
      "updatedAt": "2026-07-22T03:43:23.000Z"
    },
    {
      "id": "A7393ED51E387246BB3D6249943091E8_2305",
      "label": "2305",
      "routeId": "333",
      "mode": "bus",
      "tripId": "37822307-BT 26_27-43278",
      "headsign": "Woolloongabba station",
      "stopId": "ROMA",
      "lat": -27.465999603271484,
      "lon": 153.01954650878906,
      "bearing": null,
      "speed": null,
      "status": "stopped_at",
      "currentStopSequence": 15,
      "timestamp": 1784691828,
      "updatedAt": "2026-07-22T03:43:48.000Z"
    },
    {
      "id": "A7393ED51E387246BB3D6249943091E8_2311",
      "label": "2311",
      "routeId": "330",
      "mode": "bus",
      "tripId": "37822148-BT 26_27-43278",
      "headsign": "Queen Street station",
      "stopId": null,
      "lat": -27.31541633605957,
      "lon": 153.0335235595703,
      "bearing": null,
      "speed": null,
      "status": "in_transit_to",
      "currentStopSequence": 5,
      "timestamp": 1784691831,
      "updatedAt": "2026-07-22T03:43:51.000Z"
    },
    {
      "id": "73DD7B678B530932DF783319BBF95E95_234",
      "label": "234",
      "routeId": "750",
      "mode": "bus",
      "tripId": "37580903-SBL 26_27-42893",
      "headsign": "Broadbeach South station",
      "stopId": null,
      "lat": -28.03502655029297,
      "lon": 153.42669677734375,
      "bearing": null,
      "speed": null,
      "status": "in_transit_to",
      "currentStopSequence": 23,
      "timestamp": 1784691816,
      "updatedAt": "2026-07-22T03:43:36.000Z"
    },
    {
      "id": "A7393ED51E387246BB3D6249943091E8_2352",
      "label": "2352",
      "routeId": "330",
      "mode": "bus",
      "tripId": "37822211-BT 26_27-43278",
      "headsign": "Bracken Ridge, Quinlan St",
      "stopId": "CHMS",
      "lat": -27.38455581665039,
      "lon": 153.0306396484375,
      "bearing": null,
      "speed": null,
      "status": "in_transit_to",
      "currentStopSequence": 8,
      "timestamp": 1784691809,
      "updatedAt": "2026-07-22T03:43:29.000Z"
    },
    {
      "id": "73DD7B678B530932DF783319BBF95E95_240",
      "label": "240",
      "routeId": "700",
      "mode": "bus",
      "tripId": "37583528-SBL 26_27-42893",
      "headsign": "Broadbeach South station",
      "stopId": null,
      "lat": -28.067554473876953,
      "lon": 153.44061279296875,
      "bearing": null,
      "speed": null,
      "status": "in_transit_to",
      "currentStopSequence": 39,
      "timestamp": 1784691821,
      "updatedAt": "2026-07-22T03:43:41.000Z"
    },
    {
      "id": "73DD7B678B530932DF783319BBF95E95_244",
      "label": "244",
      "routeId": "760",
      "mode": "bus",
      "tripId": "37586870-SBL 26_27-42893",
      "headsign": "Robina Town Centre",
      "stopId": null,
      "lat": -28.16866683959961,
      "lon": 153.5391082763672,
      "bearing": null,
      "speed": null,
      "status": "in_transit_to",
      "currentStopSequence": 4,
      "timestamp": 1784691807,
      "updatedAt": "2026-07-22T03:43:27.000Z"
    },
    {
      "id": "73DD7B678B530932DF783319BBF95E95_246",
      "label": "246",
      "routeId": "760",
      "mode": "bus",
      "tripId": "37583834-SBL 26_27-42893",
      "headsign": "Tweed Heads",
      "stopId": null,
      "lat": -28.16730308532715,
      "lon": 153.52719116210938,
      "bearing": null,
      "speed": null,
      "status": "stopped_at",
      "currentStopSequence": 30,
      "timestamp": 1784691820,
      "updatedAt": "2026-07-22T03:43:40.000Z"
    },
    {
      "id": "73DD7B678B530932DF783319BBF95E95_249",
      "label": "249",
      "routeId": "700",
      "mode": "bus",
      "tripId": "37583720-SBL 26_27-42893",
      "headsign": "Tweed Heads",
      "stopId": null,
      "lat": -28.074138641357422,
      "lon": 153.4447479248047,
      "bearing": null,
      "speed": null,
      "status": "in_transit_to",
      "currentStopSequence": 7,
      "timestamp": 1784691813,
      "updatedAt": "2026-07-22T03:43:33.000Z"
    },
    {
      "id": "73DD7B678B530932DF783319BBF95E95_261",
      "label": "261",
      "routeId": "700",
      "mode": "bus",
      "tripId": "37582880-SBL 26_27-42893",
      "headsign": "Broadbeach South station",
      "stopId": null,
      "lat": -28.160722732543945,
      "lon": 153.51181030273438,
      "bearing": null,
      "speed": null,
      "status": "stopped_at",
      "currentStopSequence": 11,
      "timestamp": 1784691828,
      "updatedAt": "2026-07-22T03:43:48.000Z"
    },
    {
      "id": "A7393ED51E387246BB3D6249943091E8_2801",
      "label": "2801",
      "routeId": "444",
      "mode": "bus",
      "tripId": "37815863-BT 26_27-43278",
      "headsign": "Queensland Theatre",
      "stopId": "CULT",
      "lat": -27.475387573242188,
      "lon": 153.0156707763672,
      "bearing": null,
      "speed": null,
      "status": "in_transit_to",
      "currentStopSequence": 32,
      "timestamp": 1784691817,
      "updatedAt": "2026-07-22T03:43:37.000Z"
    },
    {
      "id": "A7393ED51E387246BB3D6249943091E8_2811",
      "label": "2811",
      "routeId": "444",
      "mode": "bus",
      "tripId": "37816153-BT 26_27-43278",
      "headsign": "Moggill, Moggill Rd",
      "stopId": null,
      "lat": -27.490694046020508,
      "lon": 152.98550415039062,
      "bearing": null,
      "speed": null,
      "status": "stopped_at",
      "currentStopSequence": 9,
      "timestamp": 1784691831,
      "updatedAt": "2026-07-22T03:43:51.000Z"
    },
    {
      "id": "A7393ED51E387246BB3D6249943091E8_2814",
      "label": "2814",
      "routeId": "444",
      "mode": "bus",
      "tripId": "37816236-BT 26_27-43278",
      "headsign": "Moggill, Moggill Rd",
      "stopId": "CULT",
      "lat": -27.47977638244629,
      "lon": 152.98304748535156,
      "bearing": null,
      "speed": null,
      "status": "in_transit_to",
      "currentStopSequence": 1,
      "timestamp": 1784686904,
      "updatedAt": "2026-07-22T02:21:44.000Z"
    },
    {
      "id": "A7393ED51E387246BB3D6249943091E8_2826",
      "label": "2826",
      "routeId": "444",
      "mode": "bus",
      "tripId": "37816154-BT 26_27-43278",
      "headsign": "Queensland Theatre",
      "stopId": null,
      "lat": -27.508638381958008,
      "lon": 152.94183349609375,
      "bearing": null,
      "speed": null,
      "status": "in_transit_to",
      "currentStopSequence": 17,
      "timestamp": 1784691828,
      "updatedAt": "2026-07-22T03:43:48.000Z"
    },
    {
      "id": "A7393ED51E387246BB3D6249943091E8_2847",
      "label": "2847",
      "routeId": "444",
      "mode": "bus",
      "tripId": "37816237-BT 26_27-43278",
      "headsign": "Queensland Theatre",
      "stopId": null,
      "lat": -27.560611724853516,
      "lon": 152.86805725097656,
      "bearing": null,
      "speed": null,
      "status": "in_transit_to",
      "currentStopSequence": 4,
      "timestamp": 1784691824,
      "updatedAt": "2026-07-22T03:43:44.000Z"
    },
    {
      "id": "A7393ED51E387246BB3D6249943091E8_2850",
      "label": "2850",
      "routeId": "444",
      "mode": "bus",
      "tripId": "37816052-BT 26_27-43278",
      "headsign": "Queensland Theatre",
      "stopId": "INDR",
      "lat": -27.500749588012695,
      "lon": 152.97183227539062,
      "bearing": null,
      "speed": null,
      "status": "stopped_at",
      "currentStopSequence": 22,
      "timestamp": 1784691818,
      "updatedAt": "2026-07-22T03:43:38.000Z"
    },
    {
      "id": "A7393ED51E387246BB3D6249943091E8_2851",
      "label": "2851",
      "routeId": "444",
      "mode": "bus",
      "tripId": "37816236-BT 26_27-43278",
      "headsign": "Moggill, Moggill Rd",
      "stopId": null,
      "lat": -27.46586036682129,
      "lon": 153.01458740234375,
      "bearing": null,
      "speed": null,
      "status": "in_transit_to",
      "currentStopSequence": 5,
      "timestamp": 1784691803,
      "updatedAt": "2026-07-22T03:43:23.000Z"
    },
    {
      "id": "A7393ED51E387246BB3D6249943091E8_2852",
      "label": "2852",
      "routeId": "444",
      "mode": "bus",
      "tripId": "37816437-BT 26_27-43278",
      "headsign": "Moggill, Moggill Rd",
      "stopId": "CULT",
      "lat": -27.479610443115234,
      "lon": 152.98333740234375,
      "bearing": null,
      "speed": null,
      "status": "in_transit_to",
      "currentStopSequence": 1,
      "timestamp": 1784691829,
      "updatedAt": "2026-07-22T03:43:49.000Z"
    },
    {
      "id": "A7393ED51E387246BB3D6249943091E8_2868",
      "label": "2868",
      "routeId": "330",
      "mode": "bus",
      "tripId": "37822212-BT 26_27-43278",
      "headsign": "Bracken Ridge, Quinlan St",
      "stopId": "CHMS",
      "lat": -27.44422149658203,
      "lon": 153.0295867919922,
      "bearing": null,
      "speed": null,
      "status": "in_transit_to",
      "currentStopSequence": 7,
      "timestamp": 1784691677,
      "updatedAt": "2026-07-22T03:41:17.000Z"
    },
    {
      "id": "A7393ED51E387246BB3D6249943091E8_2906",
      "label": "2906",
      "routeId": "444",
      "mode": "bus",
      "tripId": "37816050-BT 26_27-43278",
      "headsign": "Moggill, Moggill Rd",
      "stopId": null,
      "lat": -27.529638290405273,
      "lon": 152.91732788085938,
      "bearing": null,
      "speed": null,
      "status": "in_transit_to",
      "currentStopSequence": 20,
      "timestamp": 1784691829,
      "updatedAt": "2026-07-22T03:43:49.000Z"
    },
    {
      "id": "A7393ED51E387246BB3D6249943091E8_2934",
      "label": "2934",
      "routeId": "444",
      "mode": "bus",
      "tripId": "37815955-BT 26_27-43278",
      "headsign": "Moggill, Moggill Rd",
      "stopId": "CULT",
      "lat": -27.56452751159668,
      "lon": 152.86880493164062,
      "bearing": null,
      "speed": null,
      "status": "stopped_at",
      "currentStopSequence": 1,
      "timestamp": 1784691801,
      "updatedAt": "2026-07-22T03:43:21.000Z"
    },
    {
      "id": "A7393ED51E387246BB3D6249943091E8_2938",
      "label": "2938",
      "routeId": "444",
      "mode": "bus",
      "tripId": "37815956-BT 26_27-43278",
      "headsign": "Queensland Theatre",
      "stopId": "CULT",
      "lat": -27.47541618347168,
      "lon": 153.0157470703125,
      "bearing": null,
      "speed": null,
      "status": "in_transit_to",
      "currentStopSequence": 32,
      "timestamp": 1784691821,
      "updatedAt": "2026-07-22T03:43:41.000Z"
    },
    {
      "id": "73DD7B678B530932DF783319BBF95E95_306",
      "label": "306",
      "routeId": "700",
      "mode": "bus",
      "tripId": "37582596-SBL 26_27-42893",
      "headsign": "Tweed Heads",
      "stopId": "BBS",
      "lat": -28.036832809448242,
      "lon": 153.4318389892578,
      "bearing": null,
      "speed": null,
      "status": "in_transit_to",
      "currentStopSequence": 1,
      "timestamp": 1784691827,
      "updatedAt": "2026-07-22T03:43:47.000Z"
    },
    {
      "id": "73DD7B678B530932DF783319BBF95E95_327",
      "label": "327",
      "routeId": "750",
      "mode": "bus",
      "tripId": "37583962-SBL 26_27-42893",
      "headsign": "Robina station",
      "stopId": null,
      "lat": -28.0368595123291,
      "lon": 153.4311981201172,
      "bearing": null,
      "speed": null,
      "status": "in_transit_to",
      "currentStopSequence": 1,
      "timestamp": 1784689908,
      "updatedAt": "2026-07-22T03:11:48.000Z"
    },
    {
      "id": "06EAC06E55F06AEC6418AEEBA19D5764_36",
      "label": "36",
      "routeId": "555",
      "mode": "bus",
      "tripId": "37982549-LCBS 26_27-43389",
      "headsign": "Loganholme station",
      "stopId": null,
      "lat": -27.473915100097656,
      "lon": 153.01841735839844,
      "bearing": null,
      "speed": null,
      "status": "in_transit_to",
      "currentStopSequence": 5,
      "timestamp": 1784691829,
      "updatedAt": "2026-07-22T03:43:49.000Z"
    },
    {
      "id": "73DD7B678B530932DF783319BBF95E95_381",
      "label": "381",
      "routeId": "700",
      "mode": "bus",
      "tripId": "37586724-SBL 26_27-42893",
      "headsign": "Tweed Heads",
      "stopId": null,
      "lat": -28.044055938720703,
      "lon": 153.43479919433594,
      "bearing": null,
      "speed": null,
      "status": "in_transit_to",
      "currentStopSequence": 3,
      "timestamp": 1784691809,
      "updatedAt": "2026-07-22T03:43:29.000Z"
    },
    {
      "id": "73DD7B678B530932DF783319BBF95E95_383",
      "label": "383",
      "routeId": "750",
      "mode": "bus",
      "tripId": "37582132-SBL 26_27-42893",
      "headsign": "Broadbeach South station",
      "stopId": null,
      "lat": -28.07069206237793,
      "lon": 153.37869262695312,
      "bearing": null,
      "speed": null,
      "status": "stopped_at",
      "currentStopSequence": 1,
      "timestamp": 1784690120,
      "updatedAt": "2026-07-22T03:15:20.000Z"
    },
    {
      "id": "73DD7B678B530932DF783319BBF95E95_385",
      "label": "385",
      "routeId": "750",
      "mode": "bus",
      "tripId": "37586798-SBL 26_27-42893",
      "headsign": "Broadbeach South station",
      "stopId": "ROBINA",
      "lat": -28.071054458618164,
      "lon": 153.37716674804688,
      "bearing": null,
      "speed": null,
      "status": "in_transit_to",
      "currentStopSequence": 2,
      "timestamp": 1784691825,
      "updatedAt": "2026-07-22T03:43:45.000Z"
    },
    {
      "id": "73DD7B678B530932DF783319BBF95E95_393",
      "label": "393",
      "routeId": "700",
      "mode": "bus",
      "tripId": "37584238-SBL 26_27-42893",
      "headsign": "Broadbeach South station",
      "stopId": null,
      "lat": -28.12069320678711,
      "lon": 153.47238159179688,
      "bearing": null,
      "speed": null,
      "status": "stopped_at",
      "currentStopSequence": 24,
      "timestamp": 1784691819,
      "updatedAt": "2026-07-22T03:43:39.000Z"
    },
    {
      "id": "06EAC06E55F06AEC6418AEEBA19D5764_40",
      "label": "40",
      "routeId": "555",
      "mode": "bus",
      "tripId": "37981472-LCBS 26_27-43389",
      "headsign": "Loganholme station",
      "stopId": "LGHM",
      "lat": -27.639055252075195,
      "lon": 153.13955688476562,
      "bearing": null,
      "speed": null,
      "status": "in_transit_to",
      "currentStopSequence": 15,
      "timestamp": 1784691828,
      "updatedAt": "2026-07-22T03:43:48.000Z"
    },
    {
      "id": "73DD7B678B530932DF783319BBF95E95_446",
      "label": "446",
      "routeId": "700",
      "mode": "bus",
      "tripId": "37582335-SBL 26_27-42893",
      "headsign": "Tweed Heads",
      "stopId": null,
      "lat": -28.163555145263672,
      "lon": 153.51577758789062,
      "bearing": null,
      "speed": null,
      "status": "in_transit_to",
      "currentStopSequence": 34,
      "timestamp": 1784691823,
      "updatedAt": "2026-07-22T03:43:43.000Z"
    },
    {
      "id": "73DD7B678B530932DF783319BBF95E95_492",
      "label": "492",
      "routeId": "760",
      "mode": "bus",
      "tripId": "37581699-SBL 26_27-42893",
      "headsign": "Tweed Heads",
      "stopId": null,
      "lat": -28.124027252197266,
      "lon": 153.4649200439453,
      "bearing": null,
      "speed": null,
      "status": "in_transit_to",
      "currentStopSequence": 8,
      "timestamp": 1784691824,
      "updatedAt": "2026-07-22T03:43:44.000Z"
    },
    {
      "id": "73DD7B678B530932DF783319BBF95E95_500",
      "label": "500",
      "routeId": "760",
      "mode": "bus",
      "tripId": "37582397-SBL 26_27-42893",
      "headsign": "Robina Town Centre",
      "stopId": null,
      "lat": -28.1345272064209,
      "lon": 153.46990966796875,
      "bearing": null,
      "speed": null,
      "status": "stopped_at",
      "currentStopSequence": 25,
      "timestamp": 1784691808,
      "updatedAt": "2026-07-22T03:43:28.000Z"
    },
    {
      "id": "A7393ED51E387246BB3D6249943091E8_5004",
      "label": "5004",
      "routeId": "222",
      "mode": "bus",
      "tripId": "37816156-BT 26_27-43278",
      "headsign": "Carindale interchange",
      "stopId": null,
      "lat": -27.495943069458008,
      "lon": 153.05677795410156,
      "bearing": null,
      "speed": null,
      "status": "in_transit_to",
      "currentStopSequence": 9,
      "timestamp": 1784691830,
      "updatedAt": "2026-07-22T03:43:50.000Z"
    },
    {
      "id": "A7393ED51E387246BB3D6249943091E8_5025",
      "label": "5025",
      "routeId": "222",
      "mode": "bus",
      "tripId": "37816260-BT 26_27-43278",
      "headsign": "Roma Street station",
      "stopId": "CARI",
      "lat": -27.505250930786133,
      "lon": 153.10263061523438,
      "bearing": null,
      "speed": null,
      "status": "in_transit_to",
      "currentStopSequence": 1,
      "timestamp": 1784691811,
      "updatedAt": "2026-07-22T03:43:31.000Z"
    },
    {
      "id": "A7393ED51E387246BB3D6249943091E8_5072",
      "label": "5072",
      "routeId": "222",
      "mode": "bus",
      "tripId": "37816169-BT 26_27-43278",
      "headsign": "Roma Street station",
      "stopId": "BURA",
      "lat": -27.497583389282227,
      "lon": 153.04344177246094,
      "bearing": null,
      "speed": null,
      "status": "in_transit_to",
      "currentStopSequence": 8,
      "timestamp": 1784691808,
      "updatedAt": "2026-07-22T03:43:28.000Z"
    },
    {
      "id": "A7393ED51E387246BB3D6249943091E8_5076",
      "label": "5076",
      "routeId": "222",
      "mode": "bus",
      "tripId": "37816244-BT 26_27-43278",
      "headsign": "Carindale interchange",
      "stopId": "QSTN",
      "lat": -27.468399047851562,
      "lon": 153.02392578125,
      "bearing": null,
      "speed": null,
      "status": "stopped_at",
      "currentStopSequence": 2,
      "timestamp": 1784691803,
      "updatedAt": "2026-07-22T03:43:23.000Z"
    },
    {
      "id": "A7393ED51E387246BB3D6249943091E8_5080",
      "label": "5080",
      "routeId": "222",
      "mode": "bus",
      "tripId": "37816056-BT 26_27-43278",
      "headsign": "Carindale interchange",
      "stopId": "CARI",
      "lat": -27.50411033630371,
      "lon": 153.10305786132812,
      "bearing": null,
      "speed": null,
      "status": "in_transit_to",
      "currentStopSequence": 13,
      "timestamp": 1784691830,
      "updatedAt": "2026-07-22T03:43:50.000Z"
    },
    {
      "id": "A7393ED51E387246BB3D6249943091E8_5084",
      "label": "5084",
      "routeId": "222",
      "mode": "bus",
      "tripId": "37816339-BT 26_27-43278",
      "headsign": "Carindale interchange",
      "stopId": "ROMA",
      "lat": -27.46416664123535,
      "lon": 153.01585388183594,
      "bearing": null,
      "speed": null,
      "status": "in_transit_to",
      "currentStopSequence": 1,
      "timestamp": 1784691810,
      "updatedAt": "2026-07-22T03:43:30.000Z"
    },
    {
      "id": "A7393ED51E387246BB3D6249943091E8_5094",
      "label": "5094",
      "routeId": "222",
      "mode": "bus",
      "tripId": "37816353-BT 26_27-43278",
      "headsign": "Roma Street station",
      "stopId": "CARI",
      "lat": -27.490055084228516,
      "lon": 153.10252380371094,
      "bearing": null,
      "speed": null,
      "status": "in_transit_to",
      "currentStopSequence": 1,
      "timestamp": 1784691804,
      "updatedAt": "2026-07-22T03:43:24.000Z"
    },
    {
      "id": "A7393ED51E387246BB3D6249943091E8_5104",
      "label": "5104",
      "routeId": "169",
      "mode": "bus",
      "tripId": "37820712-BT 26_27-43278",
      "headsign": "UQ Lakes station",
      "stopId": "EMPS",
      "lat": -27.555137634277344,
      "lon": 153.02064514160156,
      "bearing": null,
      "speed": null,
      "status": "in_transit_to",
      "currentStopSequence": 1,
      "timestamp": 1784691808,
      "updatedAt": "2026-07-22T03:43:28.000Z"
    },
    {
      "id": "A7393ED51E387246BB3D6249943091E8_5122",
      "label": "5122",
      "routeId": "169",
      "mode": "bus",
      "tripId": "37820710-BT 26_27-43278",
      "headsign": "UQ Lakes station",
      "stopId": "GARD",
      "lat": -27.57036018371582,
      "lon": 153.09161376953125,
      "bearing": null,
      "speed": null,
      "status": "in_transit_to",
      "currentStopSequence": 2,
      "timestamp": 1784691827,
      "updatedAt": "2026-07-22T03:43:47.000Z"
    },
    {
      "id": "A7393ED51E387246BB3D6249943091E8_5125",
      "label": "5125",
      "routeId": "222",
      "mode": "bus",
      "tripId": "37816408-BT 26_27-43278",
      "headsign": "Carindale interchange",
      "stopId": "ROMA",
      "lat": -27.46993064880371,
      "lon": 153.02496337890625,
      "bearing": null,
      "speed": null,
      "status": "in_transit_to",
      "currentStopSequence": 1,
      "timestamp": 1784691828,
      "updatedAt": "2026-07-22T03:43:48.000Z"
    },
    {
      "id": "A7393ED51E387246BB3D6249943091E8_5157",
      "label": "5157",
      "routeId": "169",
      "mode": "bus",
      "tripId": "37820765-BT 26_27-43278",
      "headsign": "Eight Mile Plains station",
      "stopId": "UQLA",
      "lat": -27.49888801574707,
      "lon": 153.05068969726562,
      "bearing": null,
      "speed": null,
      "status": "in_transit_to",
      "currentStopSequence": 1,
      "timestamp": 1784691805,
      "updatedAt": "2026-07-22T03:43:25.000Z"
    },
    {
      "id": "06EAC06E55F06AEC6418AEEBA19D5764_52",
      "label": "52",
      "routeId": "560",
      "mode": "bus",
      "tripId": "37981970-LCBS 26_27-43389",
      "headsign": "Loganholme station",
      "stopId": null,
      "lat": -27.6525821685791,
      "lon": 153.1607208251953,
      "bearing": null,
      "speed": null,
      "status": "stopped_at",
      "currentStopSequence": 55,
      "timestamp": 1784691815,
      "updatedAt": "2026-07-22T03:43:35.000Z"
    },
    {
      "id": "06EAC06E55F06AEC6418AEEBA19D5764_55",
      "label": "55",
      "routeId": "560",
      "mode": "bus",
      "tripId": "37982226-LCBS 26_27-43389",
      "headsign": "Loganholme station",
      "stopId": "MEAD",
      "lat": -27.681026458740234,
      "lon": 153.11441040039062,
      "bearing": null,
      "speed": null,
      "status": "stopped_at",
      "currentStopSequence": 32,
      "timestamp": 1784691827,
      "updatedAt": "2026-07-22T03:43:47.000Z"
    },
    {
      "id": "06EAC06E55F06AEC6418AEEBA19D5764_555",
      "label": "555",
      "routeId": "555",
      "mode": "bus",
      "tripId": "37982692-LCBS 26_27-43389",
      "headsign": "Brisbane City",
      "stopId": "SPRW",
      "lat": -27.615055084228516,
      "lon": 153.12496948242188,
      "bearing": null,
      "speed": null,
      "status": "stopped_at",
      "currentStopSequence": 2,
      "timestamp": 1784691821,
      "updatedAt": "2026-07-22T03:43:41.000Z"
    },
    {
      "id": "06EAC06E55F06AEC6418AEEBA19D5764_56",
      "label": "56",
      "routeId": "560",
      "mode": "bus",
      "tripId": "37982074-LCBS 26_27-43389",
      "headsign": "Browns Plains",
      "stopId": "LGHM",
      "lat": -27.660415649414062,
      "lon": 153.17347717285156,
      "bearing": null,
      "speed": null,
      "status": "stopped_at",
      "currentStopSequence": 1,
      "timestamp": 1784691829,
      "updatedAt": "2026-07-22T03:43:49.000Z"
    },
    {
      "id": "06EAC06E55F06AEC6418AEEBA19D5764_69",
      "label": "69",
      "routeId": "560",
      "mode": "bus",
      "tripId": "37982568-LCBS 26_27-43389",
      "headsign": "Browns Plains",
      "stopId": null,
      "lat": -27.67452621459961,
      "lon": 153.12380981445312,
      "bearing": null,
      "speed": null,
      "status": "stopped_at",
      "currentStopSequence": 25,
      "timestamp": 1784691829,
      "updatedAt": "2026-07-22T03:43:49.000Z"
    },
    {
      "id": "06EAC06E55F06AEC6418AEEBA19D5764_7128",
      "label": "7128",
      "routeId": "560",
      "mode": "bus",
      "tripId": "37982190-LCBS 26_27-43389",
      "headsign": "Browns Plains",
      "stopId": null,
      "lat": -27.664833068847656,
      "lon": 153.03521728515625,
      "bearing": null,
      "speed": null,
      "status": "in_transit_to",
      "currentStopSequence": 58,
      "timestamp": 1784691815,
      "updatedAt": "2026-07-22T03:43:35.000Z"
    },
    {
      "id": "73DD7B678B530932DF783319BBF95E95_725",
      "label": "725",
      "routeId": "700",
      "mode": "bus",
      "tripId": "37586670-SBL 26_27-42893",
      "headsign": "Tweed Heads",
      "stopId": "BBS",
      "lat": -28.036083221435547,
      "lon": 153.4310302734375,
      "bearing": null,
      "speed": null,
      "status": "stopped_at",
      "currentStopSequence": 1,
      "timestamp": 1784690988,
      "updatedAt": "2026-07-22T03:29:48.000Z"
    },
    {
      "id": "73DD7B678B530932DF783319BBF95E95_7266",
      "label": "7266",
      "routeId": "700",
      "mode": "bus",
      "tripId": "37585479-SBL 26_27-42893",
      "headsign": "Broadbeach South station",
      "stopId": null,
      "lat": -28.102500915527344,
      "lon": 153.4625244140625,
      "bearing": null,
      "speed": null,
      "status": "stopped_at",
      "currentStopSequence": 31,
      "timestamp": 1784691826,
      "updatedAt": "2026-07-22T03:43:46.000Z"
    },
    {
      "id": "73DD7B678B530932DF783319BBF95E95_741",
      "label": "741",
      "routeId": "760",
      "mode": "bus",
      "tripId": "37582557-SBL 26_27-42893",
      "headsign": "Tweed Heads",
      "stopId": "ROBINA",
      "lat": -28.076860427856445,
      "lon": 153.3831329345703,
      "bearing": null,
      "speed": null,
      "status": "in_transit_to",
      "currentStopSequence": 1,
      "timestamp": 1784687867,
      "updatedAt": "2026-07-22T02:37:47.000Z"
    },
    {
      "id": "73DD7B678B530932DF783319BBF95E95_776",
      "label": "776",
      "routeId": "750",
      "mode": "bus",
      "tripId": "37582866-SBL 26_27-42893",
      "headsign": "Robina station",
      "stopId": null,
      "lat": -28.047443389892578,
      "lon": 153.41616821289062,
      "bearing": null,
      "speed": null,
      "status": "stopped_at",
      "currentStopSequence": 5,
      "timestamp": 1784691829,
      "updatedAt": "2026-07-22T03:43:49.000Z"
    },
    {
      "id": "06EAC06E55F06AEC6418AEEBA19D5764_81",
      "label": "81",
      "routeId": "555",
      "mode": "bus",
      "tripId": "37982470-LCBS 26_27-43389",
      "headsign": "Brisbane City",
      "stopId": null,
      "lat": -27.545804977416992,
      "lon": 153.0635223388672,
      "bearing": null,
      "speed": null,
      "status": "in_transit_to",
      "currentStopSequence": 7,
      "timestamp": 1784691809,
      "updatedAt": "2026-07-22T03:43:29.000Z"
    },
    {
      "id": "73DD7B678B530932DF783319BBF95E95_922",
      "label": "922",
      "routeId": "700",
      "mode": "bus",
      "tripId": "37584062-SBL 26_27-42893",
      "headsign": "Broadbeach South station",
      "stopId": null,
      "lat": -28.16816520690918,
      "lon": 153.5360565185547,
      "bearing": null,
      "speed": null,
      "status": "in_transit_to",
      "currentStopSequence": 5,
      "timestamp": 1784691827,
      "updatedAt": "2026-07-22T03:43:47.000Z"
    },
    {
      "id": "73DD7B678B530932DF783319BBF95E95_925",
      "label": "925",
      "routeId": "750",
      "mode": "bus",
      "tripId": "37584392-SBL 26_27-42893",
      "headsign": "Robina station",
      "stopId": null,
      "lat": -28.036720275878906,
      "lon": 153.43177795410156,
      "bearing": null,
      "speed": null,
      "status": "stopped_at",
      "currentStopSequence": 1,
      "timestamp": 1784691814,
      "updatedAt": "2026-07-22T03:43:34.000Z"
    },
    {
      "id": "73DD7B678B530932DF783319BBF95E95_926",
      "label": "926",
      "routeId": "750",
      "mode": "bus",
      "tripId": "37584379-SBL 26_27-42893",
      "headsign": "Robina station",
      "stopId": null,
      "lat": -28.085277557373047,
      "lon": 153.3951416015625,
      "bearing": null,
      "speed": null,
      "status": "stopped_at",
      "currentStopSequence": 19,
      "timestamp": 1784691817,
      "updatedAt": "2026-07-22T03:43:37.000Z"
    },
    {
      "id": "73DD7B678B530932DF783319BBF95E95_927",
      "label": "927",
      "routeId": "750",
      "mode": "bus",
      "tripId": "37583607-SBL 26_27-42893",
      "headsign": "Broadbeach South station",
      "stopId": null,
      "lat": -28.075748443603516,
      "lon": 153.41278076171875,
      "bearing": null,
      "speed": null,
      "status": "in_transit_to",
      "currentStopSequence": 10,
      "timestamp": 1784691816,
      "updatedAt": "2026-07-22T03:43:36.000Z"
    },
    {
      "id": "73DD7B678B530932DF783319BBF95E95_931",
      "label": "931",
      "routeId": "700",
      "mode": "bus",
      "tripId": "37584085-SBL 26_27-42893",
      "headsign": "Broadbeach South station",
      "stopId": null,
      "lat": -28.17130470275879,
      "lon": 153.5443878173828,
      "bearing": null,
      "speed": null,
      "status": "in_transit_to",
      "currentStopSequence": 1,
      "timestamp": 1784691821,
      "updatedAt": "2026-07-22T03:43:41.000Z"
    },
    {
      "id": "73DD7B678B530932DF783319BBF95E95_932",
      "label": "932",
      "routeId": "700",
      "mode": "bus",
      "tripId": "37584137-SBL 26_27-42893",
      "headsign": "Tweed Heads",
      "stopId": null,
      "lat": -28.146665573120117,
      "lon": 153.4979705810547,
      "bearing": null,
      "speed": null,
      "status": "stopped_at",
      "currentStopSequence": 28,
      "timestamp": 1784691828,
      "updatedAt": "2026-07-22T03:43:48.000Z"
    }
  ]
}