{
  "meta": {
    "generatedAt": "2026-07-22T06:15:32.825Z",
    "source": "build-live-from-gtfsrt.mjs",
    "feedFormat": "protobuf",
    "sourcePaths": [
      "./raw/live/vehicle-positions.pb",
      "./raw/live/tram-vehicle-positions.pb"
    ],
    "stats": {
      "rows": 1557,
      "mappedRows": 104,
      "unmappedRoutes": 1453,
      "vehicleCount": 104
    }
  },
  "vehicles": [
    {
      "id": "73DD7B678B530932DF783319BBF95E95_1008",
      "label": "1008",
      "routeId": "750",
      "mode": "bus",
      "tripId": "37582023-SBL 26_27-42893",
      "headsign": "Broadbeach South station",
      "stopId": "ROBINA",
      "lat": -28.07349967956543,
      "lon": 153.3788604736328,
      "bearing": null,
      "speed": null,
      "status": "in_transit_to",
      "currentStopSequence": 2,
      "timestamp": 1784700919,
      "updatedAt": "2026-07-22T06:15:19.000Z"
    },
    {
      "id": "73DD7B678B530932DF783319BBF95E95_101",
      "label": "101",
      "routeId": "777",
      "mode": "bus",
      "tripId": "37586961-SBL 26_27-42893",
      "headsign": "Gold Coast Airport",
      "stopId": "BBS",
      "lat": -28.037137985229492,
      "lon": 153.43124389648438,
      "bearing": null,
      "speed": null,
      "status": "in_transit_to",
      "currentStopSequence": 1,
      "timestamp": 1784700898,
      "updatedAt": "2026-07-22T06:14:58.000Z"
    },
    {
      "id": "73DD7B678B530932DF783319BBF95E95_102",
      "label": "102",
      "routeId": "777",
      "mode": "bus",
      "tripId": "37586935-SBL 26_27-42893",
      "headsign": "Gold Coast Airport",
      "stopId": null,
      "lat": -28.06255531311035,
      "lon": 153.43763732910156,
      "bearing": null,
      "speed": null,
      "status": "in_transit_to",
      "currentStopSequence": 5,
      "timestamp": 1784700903,
      "updatedAt": "2026-07-22T06:15:03.000Z"
    },
    {
      "id": "A7393ED51E387246BB3D6249943091E8_1056",
      "label": "1056",
      "routeId": "444",
      "mode": "bus",
      "tripId": "37816855-BT 26_27-43278",
      "headsign": "Moggill, Moggill Rd",
      "stopId": null,
      "lat": -27.562387466430664,
      "lon": 152.88681030273438,
      "bearing": null,
      "speed": null,
      "status": "stopped_at",
      "currentStopSequence": 25,
      "timestamp": 1784700907,
      "updatedAt": "2026-07-22T06:15:07.000Z"
    },
    {
      "id": "73DD7B678B530932DF783319BBF95E95_106",
      "label": "106",
      "routeId": "777",
      "mode": "bus",
      "tripId": "37586969-SBL 26_27-42893",
      "headsign": "Broadbeach South station",
      "stopId": null,
      "lat": -28.16672134399414,
      "lon": 153.51344299316406,
      "bearing": null,
      "speed": null,
      "status": "stopped_at",
      "currentStopSequence": 1,
      "timestamp": 1784700889,
      "updatedAt": "2026-07-22T06:14:49.000Z"
    },
    {
      "id": "06EAC06E55F06AEC6418AEEBA19D5764_107",
      "label": "107",
      "routeId": "560",
      "mode": "bus",
      "tripId": "37982315-LCBS 26_27-43389",
      "headsign": "Loganholme station",
      "stopId": null,
      "lat": -27.661611557006836,
      "lon": 153.0421142578125,
      "bearing": null,
      "speed": null,
      "status": "stopped_at",
      "currentStopSequence": 1,
      "timestamp": 1784700906,
      "updatedAt": "2026-07-22T06:15:06.000Z"
    },
    {
      "id": "73DD7B678B530932DF783319BBF95E95_109",
      "label": "109",
      "routeId": "777",
      "mode": "bus",
      "tripId": "37586971-SBL 26_27-42893",
      "headsign": "Broadbeach South station",
      "stopId": null,
      "lat": -28.109750747680664,
      "lon": 153.46617126464844,
      "bearing": null,
      "speed": null,
      "status": "in_transit_to",
      "currentStopSequence": 4,
      "timestamp": 1784700904,
      "updatedAt": "2026-07-22T06:15:04.000Z"
    },
    {
      "id": "06EAC06E55F06AEC6418AEEBA19D5764_116",
      "label": "116",
      "routeId": "560",
      "mode": "bus",
      "tripId": "37982706-LCBS 26_27-43389",
      "headsign": "Loganholme station",
      "stopId": null,
      "lat": -27.687055587768555,
      "lon": 153.0953826904297,
      "bearing": null,
      "speed": null,
      "status": "in_transit_to",
      "currentStopSequence": 26,
      "timestamp": 1784700919,
      "updatedAt": "2026-07-22T06:15:19.000Z"
    },
    {
      "id": "06EAC06E55F06AEC6418AEEBA19D5764_117",
      "label": "117",
      "routeId": "555",
      "mode": "bus",
      "tripId": "37982720-LCBS 26_27-43389",
      "headsign": "Brisbane City",
      "stopId": "SPRW",
      "lat": -27.652055740356445,
      "lon": 153.17288208007812,
      "bearing": null,
      "speed": null,
      "status": "in_transit_to",
      "currentStopSequence": 2,
      "timestamp": 1784700911,
      "updatedAt": "2026-07-22T06:15:11.000Z"
    },
    {
      "id": "06EAC06E55F06AEC6418AEEBA19D5764_16",
      "label": "16",
      "routeId": "555",
      "mode": "bus",
      "tripId": "37982700-LCBS 26_27-43389",
      "headsign": "Brisbane City",
      "stopId": null,
      "lat": -27.52252769470215,
      "lon": 153.0542449951172,
      "bearing": null,
      "speed": null,
      "status": "in_transit_to",
      "currentStopSequence": 8,
      "timestamp": 1784700901,
      "updatedAt": "2026-07-22T06:15:01.000Z"
    },
    {
      "id": "A7393ED51E387246BB3D6249943091E8_1645",
      "label": "1645",
      "routeId": "169",
      "mode": "bus",
      "tripId": "37820719-BT 26_27-43278",
      "headsign": "UQ Lakes station",
      "stopId": "EMPS",
      "lat": -27.622831344604492,
      "lon": 153.06764221191406,
      "bearing": null,
      "speed": null,
      "status": "in_transit_to",
      "currentStopSequence": 1,
      "timestamp": 1784700906,
      "updatedAt": "2026-07-22T06:15:06.000Z"
    },
    {
      "id": "A7393ED51E387246BB3D6249943091E8_1896",
      "label": "1896",
      "routeId": "333",
      "mode": "bus",
      "tripId": "37822403-BT 26_27-43278",
      "headsign": "Chermside Interchange",
      "stopId": null,
      "lat": -27.442665100097656,
      "lon": 153.03060913085938,
      "bearing": null,
      "speed": null,
      "status": "in_transit_to",
      "currentStopSequence": 11,
      "timestamp": 1784700899,
      "updatedAt": "2026-07-22T06:14:59.000Z"
    },
    {
      "id": "A7393ED51E387246BB3D6249943091E8_1903",
      "label": "1903",
      "routeId": "333",
      "mode": "bus",
      "tripId": "37822405-BT 26_27-43278",
      "headsign": "Chermside Interchange",
      "stopId": null,
      "lat": -27.493526458740234,
      "lon": 153.03636169433594,
      "bearing": null,
      "speed": null,
      "status": "in_transit_to",
      "currentStopSequence": 1,
      "timestamp": 1784700894,
      "updatedAt": "2026-07-22T06:14:54.000Z"
    },
    {
      "id": "A7393ED51E387246BB3D6249943091E8_1920",
      "label": "1920",
      "routeId": "444",
      "mode": "bus",
      "tripId": "37817577-BT 26_27-43278",
      "headsign": "Moggill, Moggill Rd",
      "stopId": "CULT",
      "lat": -27.473831176757812,
      "lon": 153.01841735839844,
      "bearing": null,
      "speed": null,
      "status": "in_transit_to",
      "currentStopSequence": 2,
      "timestamp": 1784700917,
      "updatedAt": "2026-07-22T06:15:17.000Z"
    },
    {
      "id": "A7393ED51E387246BB3D6249943091E8_1928",
      "label": "1928",
      "routeId": "333",
      "mode": "bus",
      "tripId": "37822407-BT 26_27-43278",
      "headsign": "Chermside Interchange",
      "stopId": null,
      "lat": -27.508277893066406,
      "lon": 153.02542114257812,
      "bearing": null,
      "speed": null,
      "status": "in_transit_to",
      "currentStopSequence": 1,
      "timestamp": 1784700906,
      "updatedAt": "2026-07-22T06:15:06.000Z"
    },
    {
      "id": "A7393ED51E387246BB3D6249943091E8_1968",
      "label": "1968",
      "routeId": "222",
      "mode": "bus",
      "tripId": "37817306-BT 26_27-43278",
      "headsign": "Carindale interchange",
      "stopId": null,
      "lat": -27.492748260498047,
      "lon": 153.0753631591797,
      "bearing": null,
      "speed": null,
      "status": "in_transit_to",
      "currentStopSequence": 12,
      "timestamp": 1784700895,
      "updatedAt": "2026-07-22T06:14:55.000Z"
    },
    {
      "id": "A7393ED51E387246BB3D6249943091E8_2077",
      "label": "2077",
      "routeId": "444",
      "mode": "bus",
      "tripId": "37817378-BT 26_27-43278",
      "headsign": "Queensland Theatre",
      "stopId": null,
      "lat": -27.514638900756836,
      "lon": 152.9310760498047,
      "bearing": null,
      "speed": null,
      "status": "in_transit_to",
      "currentStopSequence": 16,
      "timestamp": 1784700907,
      "updatedAt": "2026-07-22T06:15:07.000Z"
    },
    {
      "id": "A7393ED51E387246BB3D6249943091E8_2083",
      "label": "2083",
      "routeId": "444",
      "mode": "bus",
      "tripId": "37817298-BT 26_27-43278",
      "headsign": "Moggill, Moggill Rd",
      "stopId": "INDR",
      "lat": -27.498138427734375,
      "lon": 152.97052001953125,
      "bearing": null,
      "speed": null,
      "status": "in_transit_to",
      "currentStopSequence": 12,
      "timestamp": 1784700918,
      "updatedAt": "2026-07-22T06:15:18.000Z"
    },
    {
      "id": "A7393ED51E387246BB3D6249943091E8_2086",
      "label": "2086",
      "routeId": "444",
      "mode": "bus",
      "tripId": "37816754-BT 26_27-43278",
      "headsign": "Queensland Theatre",
      "stopId": "CULT",
      "lat": -27.471887588500977,
      "lon": 153.01438903808594,
      "bearing": null,
      "speed": null,
      "status": "in_transit_to",
      "currentStopSequence": 32,
      "timestamp": 1784700894,
      "updatedAt": "2026-07-22T06:14:54.000Z"
    },
    {
      "id": "A7393ED51E387246BB3D6249943091E8_2090",
      "label": "2090",
      "routeId": "444",
      "mode": "bus",
      "tripId": "37817124-BT 26_27-43278",
      "headsign": "Moggill, Moggill Rd",
      "stopId": null,
      "lat": -27.514860153198242,
      "lon": 152.92947387695312,
      "bearing": null,
      "speed": null,
      "status": "stopped_at",
      "currentStopSequence": 18,
      "timestamp": 1784700920,
      "updatedAt": "2026-07-22T06:15:20.000Z"
    },
    {
      "id": "06EAC06E55F06AEC6418AEEBA19D5764_21",
      "label": "21",
      "routeId": "560",
      "mode": "bus",
      "tripId": "37982251-LCBS 26_27-43389",
      "headsign": "Loganholme station",
      "stopId": null,
      "lat": -27.65108299255371,
      "lon": 153.07354736328125,
      "bearing": null,
      "speed": null,
      "status": "in_transit_to",
      "currentStopSequence": 1,
      "timestamp": 1784700891,
      "updatedAt": "2026-07-22T06:14:51.000Z"
    },
    {
      "id": "A7393ED51E387246BB3D6249943091E8_2122",
      "label": "2122",
      "routeId": "330",
      "mode": "bus",
      "tripId": "37822222-BT 26_27-43278",
      "headsign": "Bracken Ridge, Quinlan St",
      "stopId": null,
      "lat": -27.327804565429688,
      "lon": 153.037109375,
      "bearing": null,
      "speed": null,
      "status": "in_transit_to",
      "currentStopSequence": 21,
      "timestamp": 1784700914,
      "updatedAt": "2026-07-22T06:15:14.000Z"
    },
    {
      "id": "A7393ED51E387246BB3D6249943091E8_2136",
      "label": "2136",
      "routeId": "330",
      "mode": "bus",
      "tripId": "37822224-BT 26_27-43278",
      "headsign": "Bracken Ridge, Quinlan St",
      "stopId": "CHMS",
      "lat": -27.383583068847656,
      "lon": 153.03005981445312,
      "bearing": null,
      "speed": null,
      "status": "stopped_at",
      "currentStopSequence": 8,
      "timestamp": 1784700899,
      "updatedAt": "2026-07-22T06:14:59.000Z"
    },
    {
      "id": "A7393ED51E387246BB3D6249943091E8_2182",
      "label": "2182",
      "routeId": "330",
      "mode": "bus",
      "tripId": "37822157-BT 26_27-43278",
      "headsign": "Queen Street station",
      "stopId": null,
      "lat": -27.350055694580078,
      "lon": 153.03997802734375,
      "bearing": null,
      "speed": null,
      "status": "in_transit_to",
      "currentStopSequence": 16,
      "timestamp": 1784700918,
      "updatedAt": "2026-07-22T06:15:18.000Z"
    },
    {
      "id": "A7393ED51E387246BB3D6249943091E8_2201",
      "label": "2201",
      "routeId": "333",
      "mode": "bus",
      "tripId": "37822321-BT 26_27-43278",
      "headsign": "Woolloongabba station",
      "stopId": "CHMS",
      "lat": -27.348304748535156,
      "lon": 153.02838134765625,
      "bearing": null,
      "speed": null,
      "status": "in_transit_to",
      "currentStopSequence": 1,
      "timestamp": 1784700917,
      "updatedAt": "2026-07-22T06:15:17.000Z"
    },
    {
      "id": "A7393ED51E387246BB3D6249943091E8_2207",
      "label": "2207",
      "routeId": "330",
      "mode": "bus",
      "tripId": "37822155-BT 26_27-43278",
      "headsign": "Queen Street station",
      "stopId": "ROMA",
      "lat": -27.46038818359375,
      "lon": 153.01492309570312,
      "bearing": null,
      "speed": null,
      "status": "in_transit_to",
      "currentStopSequence": 28,
      "timestamp": 1784700902,
      "updatedAt": "2026-07-22T06:15:02.000Z"
    },
    {
      "id": "A7393ED51E387246BB3D6249943091E8_2211",
      "label": "2211",
      "routeId": "330",
      "mode": "bus",
      "tripId": "37822221-BT 26_27-43278",
      "headsign": "Bracken Ridge, Quinlan St",
      "stopId": null,
      "lat": -27.327999114990234,
      "lon": 153.03842163085938,
      "bearing": null,
      "speed": null,
      "status": "stopped_at",
      "currentStopSequence": 20,
      "timestamp": 1784700898,
      "updatedAt": "2026-07-22T06:14:58.000Z"
    },
    {
      "id": "A7393ED51E387246BB3D6249943091E8_2216",
      "label": "2216",
      "routeId": "330",
      "mode": "bus",
      "tripId": "37822226-BT 26_27-43278",
      "headsign": "Bracken Ridge, Quinlan St",
      "stopId": null,
      "lat": -27.45222282409668,
      "lon": 153.01800537109375,
      "bearing": null,
      "speed": null,
      "status": "stopped_at",
      "currentStopSequence": 4,
      "timestamp": 1784700899,
      "updatedAt": "2026-07-22T06:14:59.000Z"
    },
    {
      "id": "A7393ED51E387246BB3D6249943091E8_2217",
      "label": "2217",
      "routeId": "333",
      "mode": "bus",
      "tripId": "37822318-BT 26_27-43278",
      "headsign": "Woolloongabba station",
      "stopId": null,
      "lat": -27.45891571044922,
      "lon": 153.01513671875,
      "bearing": null,
      "speed": null,
      "status": "stopped_at",
      "currentStopSequence": 14,
      "timestamp": 1784700901,
      "updatedAt": "2026-07-22T06:15:01.000Z"
    },
    {
      "id": "A7393ED51E387246BB3D6249943091E8_2240",
      "label": "2240",
      "routeId": "333",
      "mode": "bus",
      "tripId": "37822406-BT 26_27-43278",
      "headsign": "Chermside Interchange",
      "stopId": null,
      "lat": -27.485998153686523,
      "lon": 153.0342559814453,
      "bearing": null,
      "speed": null,
      "status": "stopped_at",
      "currentStopSequence": 1,
      "timestamp": 1784700911,
      "updatedAt": "2026-07-22T06:15:11.000Z"
    },
    {
      "id": "A7393ED51E387246BB3D6249943091E8_2249",
      "label": "2249",
      "routeId": "333",
      "mode": "bus",
      "tripId": "37822322-BT 26_27-43278",
      "headsign": "Woolloongabba station",
      "stopId": "CHMS",
      "lat": -27.373138427734375,
      "lon": 153.02279663085938,
      "bearing": null,
      "speed": null,
      "status": "in_transit_to",
      "currentStopSequence": 1,
      "timestamp": 1784700918,
      "updatedAt": "2026-07-22T06:15:18.000Z"
    },
    {
      "id": "A7393ED51E387246BB3D6249943091E8_2260",
      "label": "2260",
      "routeId": "330",
      "mode": "bus",
      "tripId": "37822156-BT 26_27-43278",
      "headsign": "Queen Street station",
      "stopId": "RBWH",
      "lat": -27.4064998626709,
      "lon": 153.0323944091797,
      "bearing": null,
      "speed": null,
      "status": "in_transit_to",
      "currentStopSequence": 24,
      "timestamp": 1784700897,
      "updatedAt": "2026-07-22T06:14:57.000Z"
    },
    {
      "id": "A7393ED51E387246BB3D6249943091E8_2265",
      "label": "2265",
      "routeId": "330",
      "mode": "bus",
      "tripId": "37822158-BT 26_27-43278",
      "headsign": "Queen Street station",
      "stopId": null,
      "lat": -27.31519317626953,
      "lon": 153.03196716308594,
      "bearing": null,
      "speed": null,
      "status": "in_transit_to",
      "currentStopSequence": 6,
      "timestamp": 1784700921,
      "updatedAt": "2026-07-22T06:15:21.000Z"
    },
    {
      "id": "A7393ED51E387246BB3D6249943091E8_2272",
      "label": "2272",
      "routeId": "330",
      "mode": "bus",
      "tripId": "37822227-BT 26_27-43278",
      "headsign": "Bracken Ridge, Quinlan St",
      "stopId": "ROMA",
      "lat": -27.471303939819336,
      "lon": 153.0230255126953,
      "bearing": null,
      "speed": null,
      "status": "in_transit_to",
      "currentStopSequence": 2,
      "timestamp": 1784700914,
      "updatedAt": "2026-07-22T06:15:14.000Z"
    },
    {
      "id": "A7393ED51E387246BB3D6249943091E8_2280",
      "label": "2280",
      "routeId": "330",
      "mode": "bus",
      "tripId": "37822159-BT 26_27-43278",
      "headsign": "Queen Street station",
      "stopId": null,
      "lat": -27.32088851928711,
      "lon": 153.0484161376953,
      "bearing": null,
      "speed": null,
      "status": "stopped_at",
      "currentStopSequence": 1,
      "timestamp": 1784700898,
      "updatedAt": "2026-07-22T06:14:58.000Z"
    },
    {
      "id": "A7393ED51E387246BB3D6249943091E8_2283",
      "label": "2283",
      "routeId": "333",
      "mode": "bus",
      "tripId": "37822404-BT 26_27-43278",
      "headsign": "Chermside Interchange",
      "stopId": "QSTN",
      "lat": -27.468069076538086,
      "lon": 153.02357482910156,
      "bearing": null,
      "speed": null,
      "status": "stopped_at",
      "currentStopSequence": 5,
      "timestamp": 1784700915,
      "updatedAt": "2026-07-22T06:15:15.000Z"
    },
    {
      "id": "A7393ED51E387246BB3D6249943091E8_2310",
      "label": "2310",
      "routeId": "330",
      "mode": "bus",
      "tripId": "37822220-BT 26_27-43278",
      "headsign": "Bracken Ridge, Quinlan St",
      "stopId": null,
      "lat": -27.32644271850586,
      "lon": 153.03085327148438,
      "bearing": null,
      "speed": null,
      "status": "in_transit_to",
      "currentStopSequence": 22,
      "timestamp": 1784700913,
      "updatedAt": "2026-07-22T06:15:13.000Z"
    },
    {
      "id": "A7393ED51E387246BB3D6249943091E8_2332",
      "label": "2332",
      "routeId": "330",
      "mode": "bus",
      "tripId": "37822228-BT 26_27-43278",
      "headsign": "Bracken Ridge, Quinlan St",
      "stopId": "QSTN",
      "lat": -27.470970153808594,
      "lon": 153.02357482910156,
      "bearing": null,
      "speed": null,
      "status": "stopped_at",
      "currentStopSequence": 1,
      "timestamp": 1784700913,
      "updatedAt": "2026-07-22T06:15:13.000Z"
    },
    {
      "id": "A7393ED51E387246BB3D6249943091E8_2336",
      "label": "2336",
      "routeId": "333",
      "mode": "bus",
      "tripId": "37822323-BT 26_27-43278",
      "headsign": "Woolloongabba station",
      "stopId": "CHMS",
      "lat": -27.36544418334961,
      "lon": 153.0605010986328,
      "bearing": null,
      "speed": null,
      "status": "in_transit_to",
      "currentStopSequence": 1,
      "timestamp": 1784700919,
      "updatedAt": "2026-07-22T06:15:19.000Z"
    },
    {
      "id": "73DD7B678B530932DF783319BBF95E95_235",
      "label": "235",
      "routeId": "750",
      "mode": "bus",
      "tripId": "37581600-SBL 26_27-42893",
      "headsign": "Robina station",
      "stopId": null,
      "lat": -28.035804748535156,
      "lon": 153.43136596679688,
      "bearing": null,
      "speed": null,
      "status": "stopped_at",
      "currentStopSequence": 1,
      "timestamp": 1784700899,
      "updatedAt": "2026-07-22T06:14:59.000Z"
    },
    {
      "id": "73DD7B678B530932DF783319BBF95E95_240",
      "label": "240",
      "routeId": "700",
      "mode": "bus",
      "tripId": "37584328-SBL 26_27-42893",
      "headsign": "Broadbeach South station",
      "stopId": null,
      "lat": -28.06999969482422,
      "lon": 153.4426727294922,
      "bearing": null,
      "speed": null,
      "status": "in_transit_to",
      "currentStopSequence": 38,
      "timestamp": 1784700891,
      "updatedAt": "2026-07-22T06:14:51.000Z"
    },
    {
      "id": "73DD7B678B530932DF783319BBF95E95_249",
      "label": "249",
      "routeId": "700",
      "mode": "bus",
      "tripId": "37584164-SBL 26_27-42893",
      "headsign": "Broadbeach South station",
      "stopId": null,
      "lat": -28.168193817138672,
      "lon": 153.53636169433594,
      "bearing": null,
      "speed": null,
      "status": "in_transit_to",
      "currentStopSequence": 5,
      "timestamp": 1784700917,
      "updatedAt": "2026-07-22T06:15:17.000Z"
    },
    {
      "id": "73DD7B678B530932DF783319BBF95E95_253",
      "label": "253",
      "routeId": "700",
      "mode": "bus",
      "tripId": "37583816-SBL 26_27-42893",
      "headsign": "Tweed Heads",
      "stopId": null,
      "lat": -28.139249801635742,
      "lon": 153.49124145507812,
      "bearing": null,
      "speed": null,
      "status": "in_transit_to",
      "currentStopSequence": 26,
      "timestamp": 1784700914,
      "updatedAt": "2026-07-22T06:15:14.000Z"
    },
    {
      "id": "06EAC06E55F06AEC6418AEEBA19D5764_27",
      "label": "27",
      "routeId": "555",
      "mode": "bus",
      "tripId": "37982217-LCBS 26_27-43389",
      "headsign": "Loganholme station",
      "stopId": null,
      "lat": -27.666555404663086,
      "lon": 153.12599182128906,
      "bearing": null,
      "speed": null,
      "status": "in_transit_to",
      "currentStopSequence": 1,
      "timestamp": 1784668724,
      "updatedAt": "2026-07-21T21:18:44.000Z"
    },
    {
      "id": "A7393ED51E387246BB3D6249943091E8_2822",
      "label": "2822",
      "routeId": "444",
      "mode": "bus",
      "tripId": "37817897-BT 26_27-43278",
      "headsign": "Moggill, Moggill Rd",
      "stopId": "CULT",
      "lat": -27.44305419921875,
      "lon": 152.9426727294922,
      "bearing": null,
      "speed": null,
      "status": "in_transit_to",
      "currentStopSequence": 1,
      "timestamp": 1784700914,
      "updatedAt": "2026-07-22T06:15:14.000Z"
    },
    {
      "id": "A7393ED51E387246BB3D6249943091E8_2826",
      "label": "2826",
      "routeId": "444",
      "mode": "bus",
      "tripId": "37817214-BT 26_27-43278",
      "headsign": "Moggill, Moggill Rd",
      "stopId": null,
      "lat": -27.50986099243164,
      "lon": 152.9380340576172,
      "bearing": null,
      "speed": null,
      "status": "in_transit_to",
      "currentStopSequence": 18,
      "timestamp": 1784700905,
      "updatedAt": "2026-07-22T06:15:05.000Z"
    },
    {
      "id": "A7393ED51E387246BB3D6249943091E8_2851",
      "label": "2851",
      "routeId": "444",
      "mode": "bus",
      "tripId": "37817469-BT 26_27-43278",
      "headsign": "Moggill, Moggill Rd",
      "stopId": null,
      "lat": -27.47024917602539,
      "lon": 153.00833129882812,
      "bearing": null,
      "speed": null,
      "status": "in_transit_to",
      "currentStopSequence": 5,
      "timestamp": 1784700918,
      "updatedAt": "2026-07-22T06:15:18.000Z"
    },
    {
      "id": "A7393ED51E387246BB3D6249943091E8_2874",
      "label": "2874",
      "routeId": "330",
      "mode": "bus",
      "tripId": "37822225-BT 26_27-43278",
      "headsign": "Bracken Ridge, Quinlan St",
      "stopId": "CHMS",
      "lat": -27.393638610839844,
      "lon": 153.0308380126953,
      "bearing": null,
      "speed": null,
      "status": "in_transit_to",
      "currentStopSequence": 7,
      "timestamp": 1784700907,
      "updatedAt": "2026-07-22T06:15:07.000Z"
    },
    {
      "id": "A7393ED51E387246BB3D6249943091E8_2886",
      "label": "2886",
      "routeId": "444",
      "mode": "bus",
      "tripId": "37817379-BT 26_27-43278",
      "headsign": "Moggill, Moggill Rd",
      "stopId": "INDR",
      "lat": -27.500722885131836,
      "lon": 152.97189331054688,
      "bearing": null,
      "speed": null,
      "status": "stopped_at",
      "currentStopSequence": 11,
      "timestamp": 1784700916,
      "updatedAt": "2026-07-22T06:15:16.000Z"
    },
    {
      "id": "A7393ED51E387246BB3D6249943091E8_2895",
      "label": "2895",
      "routeId": "444",
      "mode": "bus",
      "tripId": "37817525-BT 26_27-43278",
      "headsign": "Queensland Theatre",
      "stopId": null,
      "lat": -27.5628604888916,
      "lon": 152.8732147216797,
      "bearing": null,
      "speed": null,
      "status": "in_transit_to",
      "currentStopSequence": 5,
      "timestamp": 1784700915,
      "updatedAt": "2026-07-22T06:15:15.000Z"
    },
    {
      "id": "06EAC06E55F06AEC6418AEEBA19D5764_29",
      "label": "29",
      "routeId": "555",
      "mode": "bus",
      "tripId": "37982352-LCBS 26_27-43389",
      "headsign": "Loganholme station",
      "stopId": "LGHM",
      "lat": -27.657943725585938,
      "lon": 153.16725158691406,
      "bearing": null,
      "speed": null,
      "status": "in_transit_to",
      "currentStopSequence": 15,
      "timestamp": 1784700900,
      "updatedAt": "2026-07-22T06:15:00.000Z"
    },
    {
      "id": "A7393ED51E387246BB3D6249943091E8_2905",
      "label": "2905",
      "routeId": "444",
      "mode": "bus",
      "tripId": "37817005-BT 26_27-43278",
      "headsign": "Moggill, Moggill Rd",
      "stopId": null,
      "lat": -27.56430435180664,
      "lon": 152.86927795410156,
      "bearing": null,
      "speed": null,
      "status": "stopped_at",
      "currentStopSequence": 29,
      "timestamp": 1784700921,
      "updatedAt": "2026-07-22T06:15:21.000Z"
    },
    {
      "id": "A7393ED51E387246BB3D6249943091E8_2907",
      "label": "2907",
      "routeId": "444",
      "mode": "bus",
      "tripId": "37817997-BT 26_27-43278",
      "headsign": "Moggill, Moggill Rd",
      "stopId": null,
      "lat": -27.485055923461914,
      "lon": 152.9935302734375,
      "bearing": null,
      "speed": null,
      "status": "in_transit_to",
      "currentStopSequence": 26,
      "timestamp": 1784700909,
      "updatedAt": "2026-07-22T06:15:09.000Z"
    },
    {
      "id": "06EAC06E55F06AEC6418AEEBA19D5764_3",
      "label": "3",
      "routeId": "555",
      "mode": "bus",
      "tripId": "37982217-LCBS 26_27-43389",
      "headsign": "Loganholme station",
      "stopId": "LGHM",
      "lat": -27.630748748779297,
      "lon": 153.1312713623047,
      "bearing": null,
      "speed": null,
      "status": "in_transit_to",
      "currentStopSequence": 15,
      "timestamp": 1784700900,
      "updatedAt": "2026-07-22T06:15:00.000Z"
    },
    {
      "id": "73DD7B678B530932DF783319BBF95E95_306",
      "label": "306",
      "routeId": "700",
      "mode": "bus",
      "tripId": "37582600-SBL 26_27-42893",
      "headsign": "Tweed Heads",
      "stopId": null,
      "lat": -28.048444747924805,
      "lon": 153.43594360351562,
      "bearing": null,
      "speed": null,
      "status": "in_transit_to",
      "currentStopSequence": 3,
      "timestamp": 1784700895,
      "updatedAt": "2026-07-22T06:14:55.000Z"
    },
    {
      "id": "06EAC06E55F06AEC6418AEEBA19D5764_32",
      "label": "32",
      "routeId": "560",
      "mode": "bus",
      "tripId": "37981383-LCBS 26_27-43389",
      "headsign": "Browns Plains",
      "stopId": "LGHM",
      "lat": -27.660472869873047,
      "lon": 153.17347717285156,
      "bearing": null,
      "speed": null,
      "status": "stopped_at",
      "currentStopSequence": 1,
      "timestamp": 1784700911,
      "updatedAt": "2026-07-22T06:15:11.000Z"
    },
    {
      "id": "73DD7B678B530932DF783319BBF95E95_336",
      "label": "336",
      "routeId": "700",
      "mode": "bus",
      "tripId": "37583764-SBL 26_27-42893",
      "headsign": "Tweed Heads",
      "stopId": null,
      "lat": -28.1392765045166,
      "lon": 153.49124145507812,
      "bearing": null,
      "speed": null,
      "status": "in_transit_to",
      "currentStopSequence": 26,
      "timestamp": 1784700911,
      "updatedAt": "2026-07-22T06:15:11.000Z"
    },
    {
      "id": "73DD7B678B530932DF783319BBF95E95_341",
      "label": "341",
      "routeId": "760",
      "mode": "bus",
      "tripId": "37581401-SBL 26_27-42893",
      "headsign": "Robina Town Centre",
      "stopId": null,
      "lat": -28.122777938842773,
      "lon": 153.46194458007812,
      "bearing": null,
      "speed": null,
      "status": "in_transit_to",
      "currentStopSequence": 30,
      "timestamp": 1784700900,
      "updatedAt": "2026-07-22T06:15:00.000Z"
    },
    {
      "id": "73DD7B678B530932DF783319BBF95E95_349",
      "label": "349",
      "routeId": "700",
      "mode": "bus",
      "tripId": "37586469-SBL 26_27-42893",
      "headsign": "Broadbeach South station",
      "stopId": null,
      "lat": -28.146194458007812,
      "lon": 153.49758911132812,
      "bearing": null,
      "speed": null,
      "status": "in_transit_to",
      "currentStopSequence": 16,
      "timestamp": 1784700895,
      "updatedAt": "2026-07-22T06:14:55.000Z"
    },
    {
      "id": "06EAC06E55F06AEC6418AEEBA19D5764_36",
      "label": "36",
      "routeId": "555",
      "mode": "bus",
      "tripId": "37982552-LCBS 26_27-43389",
      "headsign": "Brisbane City",
      "stopId": null,
      "lat": -27.469026565551758,
      "lon": 153.02430725097656,
      "bearing": null,
      "speed": null,
      "status": "in_transit_to",
      "currentStopSequence": 14,
      "timestamp": 1784700896,
      "updatedAt": "2026-07-22T06:14:56.000Z"
    },
    {
      "id": "73DD7B678B530932DF783319BBF95E95_364",
      "label": "364",
      "routeId": "760",
      "mode": "bus",
      "tripId": "37584024-SBL 26_27-42893",
      "headsign": "Tweed Heads",
      "stopId": null,
      "lat": -28.127166748046875,
      "lon": 153.45950317382812,
      "bearing": null,
      "speed": null,
      "status": "stopped_at",
      "currentStopSequence": 9,
      "timestamp": 1784700892,
      "updatedAt": "2026-07-22T06:14:52.000Z"
    },
    {
      "id": "73DD7B678B530932DF783319BBF95E95_376",
      "label": "376",
      "routeId": "700",
      "mode": "bus",
      "tripId": "37583982-SBL 26_27-42893",
      "headsign": "Tweed Heads",
      "stopId": null,
      "lat": -28.11574935913086,
      "lon": 153.4695587158203,
      "bearing": null,
      "speed": null,
      "status": "in_transit_to",
      "currentStopSequence": 19,
      "timestamp": 1784700890,
      "updatedAt": "2026-07-22T06:14:50.000Z"
    },
    {
      "id": "73DD7B678B530932DF783319BBF95E95_398",
      "label": "398",
      "routeId": "700",
      "mode": "bus",
      "tripId": "37581304-SBL 26_27-42893",
      "headsign": "Tweed Heads",
      "stopId": "BBS",
      "lat": -28.036582946777344,
      "lon": 153.43116760253906,
      "bearing": null,
      "speed": null,
      "status": "in_transit_to",
      "currentStopSequence": 1,
      "timestamp": 1784700372,
      "updatedAt": "2026-07-22T06:06:12.000Z"
    },
    {
      "id": "06EAC06E55F06AEC6418AEEBA19D5764_44",
      "label": "44",
      "routeId": "555",
      "mode": "bus",
      "tripId": "37982256-LCBS 26_27-43389",
      "headsign": "Loganholme station",
      "stopId": null,
      "lat": -27.498109817504883,
      "lon": 153.0399932861328,
      "bearing": null,
      "speed": null,
      "status": "in_transit_to",
      "currentStopSequence": 8,
      "timestamp": 1784700901,
      "updatedAt": "2026-07-22T06:15:01.000Z"
    },
    {
      "id": "73DD7B678B530932DF783319BBF95E95_447",
      "label": "447",
      "routeId": "750",
      "mode": "bus",
      "tripId": "37582058-SBL 26_27-42893",
      "headsign": "Broadbeach South station",
      "stopId": null,
      "lat": -28.035888671875,
      "lon": 153.42575073242188,
      "bearing": null,
      "speed": null,
      "status": "in_transit_to",
      "currentStopSequence": 22,
      "timestamp": 1784700916,
      "updatedAt": "2026-07-22T06:15:16.000Z"
    },
    {
      "id": "73DD7B678B530932DF783319BBF95E95_476",
      "label": "476",
      "routeId": "700",
      "mode": "bus",
      "tripId": "37583286-SBL 26_27-42893",
      "headsign": "Broadbeach South station",
      "stopId": null,
      "lat": -28.17130470275879,
      "lon": 153.54461669921875,
      "bearing": null,
      "speed": null,
      "status": "in_transit_to",
      "currentStopSequence": 1,
      "timestamp": 1784700507,
      "updatedAt": "2026-07-22T06:08:27.000Z"
    },
    {
      "id": "06EAC06E55F06AEC6418AEEBA19D5764_48",
      "label": "48",
      "routeId": "560",
      "mode": "bus",
      "tripId": "37982456-LCBS 26_27-43389",
      "headsign": "Loganholme station",
      "stopId": null,
      "lat": -27.66433334350586,
      "lon": 153.1504669189453,
      "bearing": null,
      "speed": null,
      "status": "in_transit_to",
      "currentStopSequence": 49,
      "timestamp": 1784700917,
      "updatedAt": "2026-07-22T06:15:17.000Z"
    },
    {
      "id": "73DD7B678B530932DF783319BBF95E95_486",
      "label": "486",
      "routeId": "760",
      "mode": "bus",
      "tripId": "37582263-SBL 26_27-42893",
      "headsign": "Tweed Heads",
      "stopId": null,
      "lat": -28.164222717285156,
      "lon": 153.51666259765625,
      "bearing": null,
      "speed": null,
      "status": "in_transit_to",
      "currentStopSequence": 28,
      "timestamp": 1784700904,
      "updatedAt": "2026-07-22T06:15:04.000Z"
    },
    {
      "id": "73DD7B678B530932DF783319BBF95E95_487",
      "label": "487",
      "routeId": "700",
      "mode": "bus",
      "tripId": "37583256-SBL 26_27-42893",
      "headsign": "Tweed Heads",
      "stopId": null,
      "lat": -28.073720932006836,
      "lon": 153.44467163085938,
      "bearing": null,
      "speed": null,
      "status": "in_transit_to",
      "currentStopSequence": 7,
      "timestamp": 1784700907,
      "updatedAt": "2026-07-22T06:15:07.000Z"
    },
    {
      "id": "73DD7B678B530932DF783319BBF95E95_490",
      "label": "490",
      "routeId": "750",
      "mode": "bus",
      "tripId": "37582321-SBL 26_27-42893",
      "headsign": "Robina station",
      "stopId": null,
      "lat": -28.0848331451416,
      "lon": 153.392333984375,
      "bearing": null,
      "speed": null,
      "status": "in_transit_to",
      "currentStopSequence": 20,
      "timestamp": 1784700909,
      "updatedAt": "2026-07-22T06:15:09.000Z"
    },
    {
      "id": "A7393ED51E387246BB3D6249943091E8_5012",
      "label": "5012",
      "routeId": "169",
      "mode": "bus",
      "tripId": "37820777-BT 26_27-43278",
      "headsign": "Eight Mile Plains station",
      "stopId": "EMPS",
      "lat": -27.567916870117188,
      "lon": 153.0871124267578,
      "bearing": null,
      "speed": null,
      "status": "in_transit_to",
      "currentStopSequence": 10,
      "timestamp": 1784700892,
      "updatedAt": "2026-07-22T06:14:52.000Z"
    },
    {
      "id": "A7393ED51E387246BB3D6249943091E8_5027",
      "label": "5027",
      "routeId": "222",
      "mode": "bus",
      "tripId": "37817011-BT 26_27-43278",
      "headsign": "Carindale interchange",
      "stopId": "ROMA",
      "lat": -27.46063804626465,
      "lon": 153.03277587890625,
      "bearing": null,
      "speed": null,
      "status": "stopped_at",
      "currentStopSequence": 1,
      "timestamp": 1784700904,
      "updatedAt": "2026-07-22T06:15:04.000Z"
    },
    {
      "id": "A7393ED51E387246BB3D6249943091E8_5031",
      "label": "5031",
      "routeId": "222",
      "mode": "bus",
      "tripId": "37817383-BT 26_27-43278",
      "headsign": "Carindale interchange",
      "stopId": null,
      "lat": -27.4959716796875,
      "lon": 153.05674743652344,
      "bearing": null,
      "speed": null,
      "status": "in_transit_to",
      "currentStopSequence": 9,
      "timestamp": 1784700919,
      "updatedAt": "2026-07-22T06:15:19.000Z"
    },
    {
      "id": "A7393ED51E387246BB3D6249943091E8_5037",
      "label": "5037",
      "routeId": "169",
      "mode": "bus",
      "tripId": "37820718-BT 26_27-43278",
      "headsign": "UQ Lakes station",
      "stopId": "UQLA",
      "lat": -27.49769401550293,
      "lon": 153.01885986328125,
      "bearing": null,
      "speed": null,
      "status": "in_transit_to",
      "currentStopSequence": 10,
      "timestamp": 1784700916,
      "updatedAt": "2026-07-22T06:15:16.000Z"
    },
    {
      "id": "A7393ED51E387246BB3D6249943091E8_5038",
      "label": "5038",
      "routeId": "169",
      "mode": "bus",
      "tripId": "37820778-BT 26_27-43278",
      "headsign": "Eight Mile Plains station",
      "stopId": "UQLA",
      "lat": -27.49772071838379,
      "lon": 153.01861572265625,
      "bearing": null,
      "speed": null,
      "status": "stopped_at",
      "currentStopSequence": 1,
      "timestamp": 1784700906,
      "updatedAt": "2026-07-22T06:15:06.000Z"
    },
    {
      "id": "A7393ED51E387246BB3D6249943091E8_5052",
      "label": "5052",
      "routeId": "169",
      "mode": "bus",
      "tripId": "37820779-BT 26_27-43278",
      "headsign": "Eight Mile Plains station",
      "stopId": "UQLA",
      "lat": -27.497777938842773,
      "lon": 153.0175018310547,
      "bearing": null,
      "speed": null,
      "status": "stopped_at",
      "currentStopSequence": 1,
      "timestamp": 1784700914,
      "updatedAt": "2026-07-22T06:15:14.000Z"
    },
    {
      "id": "A7393ED51E387246BB3D6249943091E8_5072",
      "label": "5072",
      "routeId": "222",
      "mode": "bus",
      "tripId": "37817405-BT 26_27-43278",
      "headsign": "Roma Street station",
      "stopId": null,
      "lat": -27.498859405517578,
      "lon": 153.0509490966797,
      "bearing": null,
      "speed": null,
      "status": "in_transit_to",
      "currentStopSequence": 6,
      "timestamp": 1784700897,
      "updatedAt": "2026-07-22T06:14:57.000Z"
    },
    {
      "id": "A7393ED51E387246BB3D6249943091E8_5076",
      "label": "5076",
      "routeId": "222",
      "mode": "bus",
      "tripId": "37817674-BT 26_27-43278",
      "headsign": "Carindale interchange",
      "stopId": "ROMA",
      "lat": -27.462749481201172,
      "lon": 153.01536560058594,
      "bearing": null,
      "speed": null,
      "status": "in_transit_to",
      "currentStopSequence": 1,
      "timestamp": 1784700903,
      "updatedAt": "2026-07-22T06:15:03.000Z"
    },
    {
      "id": "A7393ED51E387246BB3D6249943091E8_5077",
      "label": "5077",
      "routeId": "222",
      "mode": "bus",
      "tripId": "37817556-BT 26_27-43278",
      "headsign": "Roma Street station",
      "stopId": "CARI",
      "lat": -27.505083084106445,
      "lon": 153.10275268554688,
      "bearing": null,
      "speed": null,
      "status": "in_transit_to",
      "currentStopSequence": 1,
      "timestamp": 1784700894,
      "updatedAt": "2026-07-22T06:14:54.000Z"
    },
    {
      "id": "A7393ED51E387246BB3D6249943091E8_5080",
      "label": "5080",
      "routeId": "222",
      "mode": "bus",
      "tripId": "37817582-BT 26_27-43278",
      "headsign": "Carindale interchange",
      "stopId": "ROMA",
      "lat": -27.465694427490234,
      "lon": 153.01841735839844,
      "bearing": null,
      "speed": null,
      "status": "in_transit_to",
      "currentStopSequence": 1,
      "timestamp": 1784700906,
      "updatedAt": "2026-07-22T06:15:06.000Z"
    },
    {
      "id": "A7393ED51E387246BB3D6249943091E8_5084",
      "label": "5084",
      "routeId": "222",
      "mode": "bus",
      "tripId": "37817476-BT 26_27-43278",
      "headsign": "Carindale interchange",
      "stopId": null,
      "lat": -27.480831146240234,
      "lon": 153.0220489501953,
      "bearing": null,
      "speed": null,
      "status": "stopped_at",
      "currentStopSequence": 4,
      "timestamp": 1784700918,
      "updatedAt": "2026-07-22T06:15:18.000Z"
    },
    {
      "id": "A7393ED51E387246BB3D6249943091E8_5123",
      "label": "5123",
      "routeId": "169",
      "mode": "bus",
      "tripId": "37820780-BT 26_27-43278",
      "headsign": "Eight Mile Plains station",
      "stopId": "UQLA",
      "lat": -27.485971450805664,
      "lon": 153.03477478027344,
      "bearing": null,
      "speed": null,
      "status": "in_transit_to",
      "currentStopSequence": 1,
      "timestamp": 1784700917,
      "updatedAt": "2026-07-22T06:15:17.000Z"
    },
    {
      "id": "06EAC06E55F06AEC6418AEEBA19D5764_53",
      "label": "53",
      "routeId": "555",
      "mode": "bus",
      "tripId": "37982286-LCBS 26_27-43389",
      "headsign": "Loganholme station",
      "stopId": "EMPS",
      "lat": -27.574777603149414,
      "lon": 153.09902954101562,
      "bearing": null,
      "speed": null,
      "status": "in_transit_to",
      "currentStopSequence": 12,
      "timestamp": 1784700911,
      "updatedAt": "2026-07-22T06:15:11.000Z"
    },
    {
      "id": "06EAC06E55F06AEC6418AEEBA19D5764_55",
      "label": "55",
      "routeId": "555",
      "mode": "bus",
      "tripId": "37982231-LCBS 26_27-43389",
      "headsign": "Brisbane City",
      "stopId": "LGHM",
      "lat": -27.660694122314453,
      "lon": 153.17385864257812,
      "bearing": null,
      "speed": null,
      "status": "stopped_at",
      "currentStopSequence": 1,
      "timestamp": 1784700911,
      "updatedAt": "2026-07-22T06:15:11.000Z"
    },
    {
      "id": "06EAC06E55F06AEC6418AEEBA19D5764_555",
      "label": "555",
      "routeId": "555",
      "mode": "bus",
      "tripId": "37982695-LCBS 26_27-43389",
      "headsign": "Loganholme station",
      "stopId": "CULT",
      "lat": -27.471359252929688,
      "lon": 153.02255249023438,
      "bearing": null,
      "speed": null,
      "status": "in_transit_to",
      "currentStopSequence": 4,
      "timestamp": 1784700916,
      "updatedAt": "2026-07-22T06:15:16.000Z"
    },
    {
      "id": "06EAC06E55F06AEC6418AEEBA19D5764_56",
      "label": "56",
      "routeId": "555",
      "mode": "bus",
      "tripId": "37982076-LCBS 26_27-43389",
      "headsign": "Loganholme station",
      "stopId": "SPRW",
      "lat": -27.61519432067871,
      "lon": 153.12435913085938,
      "bearing": null,
      "speed": null,
      "status": "stopped_at",
      "currentStopSequence": 14,
      "timestamp": 1784700915,
      "updatedAt": "2026-07-22T06:15:15.000Z"
    },
    {
      "id": "A7393ED51E387246BB3D6249943091E8_7141",
      "label": "7141",
      "routeId": "333",
      "mode": "bus",
      "tripId": "37822317-BT 26_27-43278",
      "headsign": "Woolloongabba station",
      "stopId": "ROMA",
      "lat": -27.460277557373047,
      "lon": 153.01499938964844,
      "bearing": null,
      "speed": null,
      "status": "in_transit_to",
      "currentStopSequence": 15,
      "timestamp": 1784700910,
      "updatedAt": "2026-07-22T06:15:10.000Z"
    },
    {
      "id": "A7393ED51E387246BB3D6249943091E8_7173",
      "label": "7173",
      "routeId": "333",
      "mode": "bus",
      "tripId": "37822409-BT 26_27-43278",
      "headsign": "Chermside Interchange",
      "stopId": null,
      "lat": -27.48583221435547,
      "lon": 153.03363037109375,
      "bearing": null,
      "speed": null,
      "status": "stopped_at",
      "currentStopSequence": 1,
      "timestamp": 1784700907,
      "updatedAt": "2026-07-22T06:15:07.000Z"
    },
    {
      "id": "A7393ED51E387246BB3D6249943091E8_7181",
      "label": "7181",
      "routeId": "333",
      "mode": "bus",
      "tripId": "37822320-BT 26_27-43278",
      "headsign": "Woolloongabba station",
      "stopId": null,
      "lat": -27.3938045501709,
      "lon": 153.031005859375,
      "bearing": null,
      "speed": null,
      "status": "stopped_at",
      "currentStopSequence": 3,
      "timestamp": 1784700913,
      "updatedAt": "2026-07-22T06:15:13.000Z"
    },
    {
      "id": "A7393ED51E387246BB3D6249943091E8_7189",
      "label": "7189",
      "routeId": "333",
      "mode": "bus",
      "tripId": "37822401-BT 26_27-43278",
      "headsign": "Chermside Interchange",
      "stopId": "CHMS",
      "lat": -27.39241600036621,
      "lon": 153.03111267089844,
      "bearing": null,
      "speed": null,
      "status": "in_transit_to",
      "currentStopSequence": 19,
      "timestamp": 1784700919,
      "updatedAt": "2026-07-22T06:15:19.000Z"
    },
    {
      "id": "A7393ED51E387246BB3D6249943091E8_7213",
      "label": "7213",
      "routeId": "333",
      "mode": "bus",
      "tripId": "37822402-BT 26_27-43278",
      "headsign": "Chermside Interchange",
      "stopId": null,
      "lat": -27.43699836730957,
      "lon": 153.03114318847656,
      "bearing": null,
      "speed": null,
      "status": "in_transit_to",
      "currentStopSequence": 11,
      "timestamp": 1784700912,
      "updatedAt": "2026-07-22T06:15:12.000Z"
    },
    {
      "id": "A7393ED51E387246BB3D6249943091E8_7214",
      "label": "7214",
      "routeId": "333",
      "mode": "bus",
      "tripId": "37822319-BT 26_27-43278",
      "headsign": "Woolloongabba station",
      "stopId": null,
      "lat": -27.427471160888672,
      "lon": 153.0328826904297,
      "bearing": null,
      "speed": null,
      "status": "stopped_at",
      "currentStopSequence": 9,
      "timestamp": 1784700917,
      "updatedAt": "2026-07-22T06:15:17.000Z"
    },
    {
      "id": "73DD7B678B530932DF783319BBF95E95_724",
      "label": "724",
      "routeId": "700",
      "mode": "bus",
      "tripId": "37582799-SBL 26_27-42893",
      "headsign": "Broadbeach South station",
      "stopId": null,
      "lat": -28.11924934387207,
      "lon": 153.47149658203125,
      "bearing": null,
      "speed": null,
      "status": "stopped_at",
      "currentStopSequence": 25,
      "timestamp": 1784700917,
      "updatedAt": "2026-07-22T06:15:17.000Z"
    },
    {
      "id": "73DD7B678B530932DF783319BBF95E95_725",
      "label": "725",
      "routeId": "700",
      "mode": "bus",
      "tripId": "37586672-SBL 26_27-42893",
      "headsign": "Broadbeach South station",
      "stopId": null,
      "lat": -28.09780502319336,
      "lon": 153.45602416992188,
      "bearing": null,
      "speed": null,
      "status": "in_transit_to",
      "currentStopSequence": 33,
      "timestamp": 1784700918,
      "updatedAt": "2026-07-22T06:15:18.000Z"
    },
    {
      "id": "06EAC06E55F06AEC6418AEEBA19D5764_77",
      "label": "77",
      "routeId": "560",
      "mode": "bus",
      "tripId": "37982673-LCBS 26_27-43389",
      "headsign": "Browns Plains",
      "stopId": null,
      "lat": -27.688610076904297,
      "lon": 153.04550170898438,
      "bearing": null,
      "speed": null,
      "status": "in_transit_to",
      "currentStopSequence": 48,
      "timestamp": 1784700919,
      "updatedAt": "2026-07-22T06:15:19.000Z"
    },
    {
      "id": "06EAC06E55F06AEC6418AEEBA19D5764_79",
      "label": "79",
      "routeId": "555",
      "mode": "bus",
      "tripId": "37981729-LCBS 26_27-43389",
      "headsign": "Loganholme station",
      "stopId": "SPRW",
      "lat": -27.61491584777832,
      "lon": 153.12466430664062,
      "bearing": null,
      "speed": null,
      "status": "stopped_at",
      "currentStopSequence": 14,
      "timestamp": 1784700898,
      "updatedAt": "2026-07-22T06:14:58.000Z"
    },
    {
      "id": "06EAC06E55F06AEC6418AEEBA19D5764_9",
      "label": "9",
      "routeId": "555",
      "mode": "bus",
      "tripId": "37982138-LCBS 26_27-43389",
      "headsign": "Brisbane City",
      "stopId": "LGHM",
      "lat": -27.66061019897461,
      "lon": 153.17361450195312,
      "bearing": null,
      "speed": null,
      "status": "stopped_at",
      "currentStopSequence": 1,
      "timestamp": 1784700910,
      "updatedAt": "2026-07-22T06:15:10.000Z"
    },
    {
      "id": "73DD7B678B530932DF783319BBF95E95_924",
      "label": "924",
      "routeId": "760",
      "mode": "bus",
      "tripId": "37584004-SBL 26_27-42893",
      "headsign": "Tweed Heads",
      "stopId": "ROBINA",
      "lat": -28.076053619384766,
      "lon": 153.38255310058594,
      "bearing": null,
      "speed": null,
      "status": "in_transit_to",
      "currentStopSequence": 1,
      "timestamp": 1784700797,
      "updatedAt": "2026-07-22T06:13:17.000Z"
    },
    {
      "id": "73DD7B678B530932DF783319BBF95E95_926",
      "label": "926",
      "routeId": "700",
      "mode": "bus",
      "tripId": "37584385-SBL 26_27-42893",
      "headsign": "Broadbeach South station",
      "stopId": "BURLEIGH",
      "lat": -28.092748641967773,
      "lon": 153.45391845703125,
      "bearing": null,
      "speed": null,
      "status": "in_transit_to",
      "currentStopSequence": 35,
      "timestamp": 1784700890,
      "updatedAt": "2026-07-22T06:14:50.000Z"
    },
    {
      "id": "73DD7B678B530932DF783319BBF95E95_927",
      "label": "927",
      "routeId": "760",
      "mode": "bus",
      "tripId": "37584351-SBL 26_27-42893",
      "headsign": "Robina Town Centre",
      "stopId": null,
      "lat": -28.168359756469727,
      "lon": 153.5373077392578,
      "bearing": null,
      "speed": null,
      "status": "stopped_at",
      "currentStopSequence": 4,
      "timestamp": 1784700911,
      "updatedAt": "2026-07-22T06:15:11.000Z"
    },
    {
      "id": "73DD7B678B530932DF783319BBF95E95_928",
      "label": "928",
      "routeId": "700",
      "mode": "bus",
      "tripId": "37583573-SBL 26_27-42893",
      "headsign": "Tweed Heads",
      "stopId": "BBS",
      "lat": -28.036470413208008,
      "lon": 153.4310760498047,
      "bearing": null,
      "speed": null,
      "status": "in_transit_to",
      "currentStopSequence": 1,
      "timestamp": 1784699227,
      "updatedAt": "2026-07-22T05:47:07.000Z"
    },
    {
      "id": "73DD7B678B530932DF783319BBF95E95_932",
      "label": "932",
      "routeId": "750",
      "mode": "bus",
      "tripId": "37584143-SBL 26_27-42893",
      "headsign": "Broadbeach South station",
      "stopId": null,
      "lat": -28.07269287109375,
      "lon": 153.41488647460938,
      "bearing": null,
      "speed": null,
      "status": "stopped_at",
      "currentStopSequence": 10,
      "timestamp": 1784700916,
      "updatedAt": "2026-07-22T06:15:16.000Z"
    },
    {
      "id": "73DD7B678B530932DF783319BBF95E95_970",
      "label": "970",
      "routeId": "750",
      "mode": "bus",
      "tripId": "37582720-SBL 26_27-42893",
      "headsign": "Robina station",
      "stopId": null,
      "lat": -28.050722122192383,
      "lon": 153.41900634765625,
      "bearing": null,
      "speed": null,
      "status": "in_transit_to",
      "currentStopSequence": 7,
      "timestamp": 1784700916,
      "updatedAt": "2026-07-22T06:15:16.000Z"
    },
    {
      "id": "73DD7B678B530932DF783319BBF95E95_979",
      "label": "979",
      "routeId": "750",
      "mode": "bus",
      "tripId": "37586230-SBL 26_27-42893",
      "headsign": "Broadbeach South station",
      "stopId": null,
      "lat": -28.078638076782227,
      "lon": 153.38302612304688,
      "bearing": null,
      "speed": null,
      "status": "in_transit_to",
      "currentStopSequence": 1,
      "timestamp": 1784700896,
      "updatedAt": "2026-07-22T06:14:56.000Z"
    }
  ]
}